{
    "0": {
        "ID": "5825",
        "Inscrito": "04861894140",
        "Nome": "EDER VELOSO MACHADO",
        "E-mail": "eder.veloso@estudante.ifgoiano.edu.br"
    },
    "1": {
        "ID": "6305",
        "Inscrito": "04563685151",
        "Nome": "VIT\u00d3RIA RAFAELA",
        "E-mail": "vitoriarafavida02@gmail.com"
    },
    "2": {
        "ID": "6751",
        "Inscrito": "70495911143",
        "Nome": "HIGOR LOUREN\u00c7O ALVES",
        "E-mail": "higor.lourenco@estudante.ifgoiano.edu.br"
    },
    "3": {
        "ID": "6771",
        "Inscrito": "06873463396",
        "Nome": "BRUNA HENRIQUE LOIOLA",
        "E-mail": "bruna.loiola@estudante.ifgoiano.edu.br"
    },
    "4": {
        "ID": "6825",
        "Inscrito": "03614286185",
        "Nome": "NARA ALINNE NOBRE DA SILVA",
        "E-mail": "nara.silva@ifgoiano.edu.br"
    },
    "5": {
        "ID": "6907",
        "Inscrito": "05921187119",
        "Nome": "JO\u00c3O PAULO RODRIGUES CARVALHO",
        "E-mail": "joao.carvalho1@estudante.ifgoiano.edu.br"
    },
    "6": {
        "ID": "7034",
        "Inscrito": "83930558149",
        "Nome": "ADRIANE DA SILVEIRA GOMES",
        "E-mail": "adriane.gomes@ifgoiano.edu.br"
    },
    "7": {
        "ID": "7076",
        "Inscrito": "71551153122",
        "Nome": "GEOVANNA LYSSA RODRIGUES MAR\u00c7AL",
        "E-mail": "geoanna.marcal@estudante.ifgoiano.edu.br"
    },
    "8": {
        "ID": "7221",
        "Inscrito": "08534710104",
        "Nome": "GUILHERME BATISTA DA SILVA",
        "E-mail": "gs333657@gmail.com"
    },
    "9": {
        "ID": "7495",
        "Inscrito": "04055761104",
        "Nome": "LUIS FELIPE SANTOS GARCIA",
        "E-mail": "luis.garcia@estudante.ifgoiano.edu.br"
    },
    "10": {
        "ID": "7626",
        "Inscrito": "06475588156",
        "Nome": "CRISTTY HELLEN BORGES NUNES",
        "E-mail": "cristty.nunes@estudante.ifgoiano.edu.br"
    },
    "11": {
        "ID": "8044",
        "Inscrito": "06430281108",
        "Nome": "DANDARA LUANA SILVA CECCATTO",
        "E-mail": "dandara.ceccatto@estudante.ifgoiano.edu.br"
    },
    "12": {
        "ID": "8530",
        "Inscrito": "06704790128",
        "Nome": "ST\u00c9FANNY DE SOUZA FREITAS DOS SANTOS",
        "E-mail": "stefanny.freitas@estudante.ifgoiano.edu.br"
    },
    "13": {
        "ID": "8539",
        "Inscrito": "04401504186",
        "Nome": "NARIA HEYCLA BEATRIZ DE JESUS CARVALHO",
        "E-mail": "naria.heycla@estudante.ifgoiano.edu.br"
    }
}