{
    "0": {
        "ID": "5796",
        "Inscrito": "06581214132",
        "Nome": "GUSTAVO BORGES ALVES",
        "E-mail": "gustavo.borges1@estudante.ifgoiano.edu.br",
        "Atividades": "Participa\u00e7\u00e3o no evento, Oficina 1- Produ\u00e7\u00e3o de alimentos a partir de plantas medicinais, Palestra de abertura: Indicadores de pH e o diagn\u00f3stico molecular de doen\u00e7as infecciosas: desenvolvimento de um teste molecular de baixo custo, Confer\u00eancia de abertura e momento cultural, Cerim\u00f4nia de encerramento, Palestra de encerramento: O processo de implanta\u00e7\u00e3o de um aterro controlado em um munic\u00edpio de pequeno porte: desafios e perspectivas",
        "A\u00e7\u00f5es": "\u00a0\u00a0 \u00a0\u00a0 \u00a0\u00a0"
    },
    "1": {
        "ID": "5810",
        "Inscrito": "08396543160",
        "Nome": "LIANDRA FERNANDES MARTINS",
        "E-mail": "liandra.fernandes@estudante.ifgoiano.edu.br",
        "Atividades": "Participa\u00e7\u00e3o no evento, Oficina 3: ISSO MINHA AV\u00d3 J\u00c1 FAZIA! Uma perspectiva t\u00e9cnica da produ\u00e7\u00e3o sustent\u00e1vel de sab\u00e3o e sabonete l\u00edquido",
        "A\u00e7\u00f5es": "\u00a0\u00a0 \u00a0\u00a0 \u00a0\u00a0"
    },
    "2": {
        "ID": "5825",
        "Inscrito": "04861894140",
        "Nome": "EDER VELOSO MACHADO",
        "E-mail": "eder.veloso@estudante.ifgoiano.edu.br",
        "Atividades": "Participa\u00e7\u00e3o no evento, Oficina 1- Produ\u00e7\u00e3o de alimentos a partir de plantas medicinais, Gincana, Oficina 8- Cultura Maker no Ensino de Qu\u00edmica: o uso do ardu\u00edno e impress\u00e3o 3D (exclusiva para discentes da Licenciatura)",
        "A\u00e7\u00f5es": "\u00a0\u00a0 \u00a0\u00a0 \u00a0\u00a0"
    },
    "3": {
        "ID": "6104",
        "Inscrito": "71268738166",
        "Nome": "N\u00c1DIA PAOLA DOS SANTOS",
        "E-mail": "nadia.santos@estudante.ifgoiano.edu.br",
        "Atividades": "Participa\u00e7\u00e3o no evento, Oficina 1- Produ\u00e7\u00e3o de alimentos a partir de plantas medicinais, Gincana",
        "A\u00e7\u00f5es": "\u00a0\u00a0 \u00a0\u00a0 \u00a0\u00a0"
    },
    "4": {
        "ID": "6105",
        "Inscrito": "03089161150",
        "Nome": "BEATRIZ TEIXEIRA FARIA",
        "E-mail": "beatriz.teixeira@estudante.ifgoiano.edu.br",
        "Atividades": "Participa\u00e7\u00e3o no evento, Oficina 1- Produ\u00e7\u00e3o de alimentos a partir de plantas medicinais, Gincana",
        "A\u00e7\u00f5es": "\u00a0\u00a0 \u00a0\u00a0 \u00a0\u00a0"
    },
    "5": {
        "ID": "6106",
        "Inscrito": "08347801193",
        "Nome": "MYLENA SANTOS RODRIGUES",
        "E-mail": "mylena.santos@estudante.ifgoiano.edu.br",
        "Atividades": "Participa\u00e7\u00e3o no evento, Oficina 1- Produ\u00e7\u00e3o de alimentos a partir de plantas medicinais, Gincana",
        "A\u00e7\u00f5es": "\u00a0\u00a0 \u00a0\u00a0 \u00a0\u00a0"
    },
    "6": {
        "ID": "6107",
        "Inscrito": "06626573144",
        "Nome": "ANNA PIETRA VITORIA LE\u00d3N BASTOS MOREIRA",
        "E-mail": "anna.pietra@estudante.ifgoiano.edu.br",
        "Atividades": "Participa\u00e7\u00e3o no evento, Oficina 1- Produ\u00e7\u00e3o de alimentos a partir de plantas medicinais, Gincana",
        "A\u00e7\u00f5es": "\u00a0\u00a0 \u00a0\u00a0 \u00a0\u00a0"
    },
    "7": {
        "ID": "6108",
        "Inscrito": "05292652148",
        "Nome": "LAINE RODRIGUES BARROS",
        "E-mail": "laine.rodrigues@estudante.ifgoiano.edu.br",
        "Atividades": "Participa\u00e7\u00e3o no evento, Oficina 1- Produ\u00e7\u00e3o de alimentos a partir de plantas medicinais, Gincana, Oficina 6- Qu\u00edmica para um mundo sustent\u00e1vel: uma abordagem investigativa para o ensino de Qu\u00edmica Verde (exclusiva para discentes da Licenciatura), Palestra de abertura: Indicadores de pH e o diagn\u00f3stico molecular de doen\u00e7as infecciosas: desenvolvimento de um teste molecular de baixo custo, Confer\u00eancia de abertura e momento cultural, Cerim\u00f4nia de encerramento, Palestra de encerramento: O processo de implanta\u00e7\u00e3o de um aterro controlado em um munic\u00edpio de pequeno porte: desafios e perspectivas, Credenciamento vespertino, Credenciamento noturno",
        "A\u00e7\u00f5es": "\u00a0\u00a0 \u00a0\u00a0 \u00a0\u00a0"
    },
    "8": {
        "ID": "6109",
        "Inscrito": "05668707113",
        "Nome": "DANIELLY RODRIGUES DOS SANTOS",
        "E-mail": "danielly.rodrigues@estudante.ifgoiano.edu.br",
        "Atividades": "Participa\u00e7\u00e3o no evento, Oficina 4: 5Rs da Sustentabilidade, Gincana",
        "A\u00e7\u00f5es": "\u00a0\u00a0 \u00a0\u00a0 \u00a0\u00a0"
    },
    "9": {
        "ID": "6110",
        "Inscrito": "06626014161",
        "Nome": "MARISSOL VIEIRA DE MORAIS",
        "E-mail": "marissol.morais@estudante.ifgoiano.edu.br",
        "Atividades": "Participa\u00e7\u00e3o no evento, Oficina 7:  Produ\u00e7\u00e3o e utiliza\u00e7\u00e3o de extratos de produtos naturais para controle de fitopat\u00f3genos  (exclusiva para discentes da Licenciatura), Oficina 1- Produ\u00e7\u00e3o de alimentos a partir de plantas medicinais, Gincana",
        "A\u00e7\u00f5es": "\u00a0\u00a0 \u00a0\u00a0 \u00a0\u00a0"
    },
    "10": {
        "ID": "6111",
        "Inscrito": "04884794109",
        "Nome": "SALETTE SOARES SILVA",
        "E-mail": "salette.soares@estudante.ifgoiano.edu.br",
        "Atividades": "Participa\u00e7\u00e3o no evento, Oficina 4: 5Rs da Sustentabilidade, Gincana",
        "A\u00e7\u00f5es": "\u00a0\u00a0 \u00a0\u00a0 \u00a0\u00a0"
    },
    "11": {
        "ID": "6112",
        "Inscrito": "08086343138",
        "Nome": "MARINA SILVA FERREIRA",
        "E-mail": "ms4286973@gmail.com",
        "Atividades": "Participa\u00e7\u00e3o no evento, Oficina 4: 5Rs da Sustentabilidade, Gincana",
        "A\u00e7\u00f5es": "\u00a0\u00a0 \u00a0\u00a0 \u00a0\u00a0"
    },
    "12": {
        "ID": "6113",
        "Inscrito": "05269205130",
        "Nome": "EDNA HELLEN MESSIAS",
        "E-mail": "edna.hellen@estudante.ifgoiano.edu.br",
        "Atividades": "Participa\u00e7\u00e3o no evento, Oficina 3: ISSO MINHA AV\u00d3 J\u00c1 FAZIA! Uma perspectiva t\u00e9cnica da produ\u00e7\u00e3o sustent\u00e1vel de sab\u00e3o e sabonete l\u00edquido",
        "A\u00e7\u00f5es": "\u00a0\u00a0 \u00a0\u00a0 \u00a0\u00a0"
    },
    "13": {
        "ID": "6114",
        "Inscrito": "71257581180",
        "Nome": "MAYRA RAFAIANI ROSA CAVALCANTE",
        "E-mail": "mayra.cavalcante@estudante.ifgoiano.edu.br",
        "Atividades": "Participa\u00e7\u00e3o no evento, Oficina 3: ISSO MINHA AV\u00d3 J\u00c1 FAZIA! Uma perspectiva t\u00e9cnica da produ\u00e7\u00e3o sustent\u00e1vel de sab\u00e3o e sabonete l\u00edquido",
        "A\u00e7\u00f5es": "\u00a0\u00a0 \u00a0\u00a0 \u00a0\u00a0"
    },
    "14": {
        "ID": "6115",
        "Inscrito": "08370490166",
        "Nome": "GUSTAVO AGUIAR DE MORAES CUNHA",
        "E-mail": "gustavo.aguiar@estudante.ifgoiano.edu.br",
        "Atividades": "Participa\u00e7\u00e3o no evento, Oficina 7:  Produ\u00e7\u00e3o e utiliza\u00e7\u00e3o de extratos de produtos naturais para controle de fitopat\u00f3genos  (exclusiva para discentes da Licenciatura), Oficina 1- Produ\u00e7\u00e3o de alimentos a partir de plantas medicinais, Gincana",
        "A\u00e7\u00f5es": "\u00a0\u00a0 \u00a0\u00a0 \u00a0\u00a0"
    },
    "15": {
        "ID": "6116",
        "Inscrito": "01873251114",
        "Nome": "ANNA CLARA LIMA FERREIRA",
        "E-mail": "anna.lima@estudante.ifgoiano.edu.br",
        "Atividades": "Participa\u00e7\u00e3o no evento, Oficina 1- Produ\u00e7\u00e3o de alimentos a partir de plantas medicinais, Gincana",
        "A\u00e7\u00f5es": "\u00a0\u00a0 \u00a0\u00a0 \u00a0\u00a0"
    },
    "16": {
        "ID": "6117",
        "Inscrito": "02869983190",
        "Nome": "JOS\u00c9 BARBOSA CESAR NETO",
        "E-mail": "jose.barbosa@estudante.ifgoiano.edu.br",
        "Atividades": "Participa\u00e7\u00e3o no evento, Gincana, Oficina 3: ISSO MINHA AV\u00d3 J\u00c1 FAZIA! Uma perspectiva t\u00e9cnica da produ\u00e7\u00e3o sustent\u00e1vel de sab\u00e3o e sabonete l\u00edquido",
        "A\u00e7\u00f5es": "\u00a0\u00a0 \u00a0\u00a0 \u00a0\u00a0"
    },
    "17": {
        "ID": "6118",
        "Inscrito": "02516725140",
        "Nome": "MARCELLA ALVES FERREIRA",
        "E-mail": "marcella.alves@estudante.ifgoiano.edu.br",
        "Atividades": "Participa\u00e7\u00e3o no evento, Oficina 7:  Produ\u00e7\u00e3o e utiliza\u00e7\u00e3o de extratos de produtos naturais para controle de fitopat\u00f3genos  (exclusiva para discentes da Licenciatura), Oficina 1- Produ\u00e7\u00e3o de alimentos a partir de plantas medicinais, Gincana",
        "A\u00e7\u00f5es": "\u00a0\u00a0 \u00a0\u00a0 \u00a0\u00a0"
    },
    "18": {
        "ID": "6119",
        "Inscrito": "70782290108",
        "Nome": "ANA FLAVIA RIBEIRO VENANCIO DA SILVA",
        "E-mail": "ana.venancio@estudante.ifgoiano.edu.br",
        "Atividades": "Participa\u00e7\u00e3o no evento, Oficina 4: 5Rs da Sustentabilidade, Gincana, Palestra de abertura: Indicadores de pH e o diagn\u00f3stico molecular de doen\u00e7as infecciosas: desenvolvimento de um teste molecular de baixo custo, Confer\u00eancia de abertura e momento cultural, Credenciamento vespertino",
        "A\u00e7\u00f5es": "\u00a0\u00a0 \u00a0\u00a0 \u00a0\u00a0"
    },
    "19": {
        "ID": "6120",
        "Inscrito": "71060079194",
        "Nome": "MARIA EDUARDA LIMA ALMEIDA",
        "E-mail": "maria.lima2@estudante.ifgoiano.edu.br",
        "Atividades": "Participa\u00e7\u00e3o no evento, Oficina 1- Produ\u00e7\u00e3o de alimentos a partir de plantas medicinais, Gincana",
        "A\u00e7\u00f5es": "\u00a0\u00a0 \u00a0\u00a0 \u00a0\u00a0"
    },
    "20": {
        "ID": "6121",
        "Inscrito": "71354776186",
        "Nome": "MARIA EDUARDA SANTOS DIAS",
        "E-mail": "maria.santos2@estudante.ifgoiano.edu.br",
        "Atividades": "Participa\u00e7\u00e3o no evento, Oficina 7:  Produ\u00e7\u00e3o e utiliza\u00e7\u00e3o de extratos de produtos naturais para controle de fitopat\u00f3genos  (exclusiva para discentes da Licenciatura), Oficina 1- Produ\u00e7\u00e3o de alimentos a partir de plantas medicinais, Gincana",
        "A\u00e7\u00f5es": "\u00a0\u00a0 \u00a0\u00a0 \u00a0\u00a0"
    },
    "21": {
        "ID": "6122",
        "Inscrito": "70040253147",
        "Nome": "MARIA LUISA DE LIMA VIEIRA",
        "E-mail": "maria.luisa2@estudante.ifgoiano.edu.br",
        "Atividades": "Participa\u00e7\u00e3o no evento, Gincana",
        "A\u00e7\u00f5es": "\u00a0\u00a0 \u00a0\u00a0 \u00a0\u00a0"
    },
    "22": {
        "ID": "6123",
        "Inscrito": "04827765103",
        "Nome": "LANNA VIT\\XC3\\XB3RIA RODRIGUES OLIVEIRA",
        "E-mail": "lanna.vitoria@estudante.ifgoiano.edu.br",
        "Atividades": "Participa\u00e7\u00e3o no evento, Oficina 1- Produ\u00e7\u00e3o de alimentos a partir de plantas medicinais, Gincana",
        "A\u00e7\u00f5es": "\u00a0\u00a0 \u00a0\u00a0 \u00a0\u00a0"
    },
    "23": {
        "ID": "6124",
        "Inscrito": "07251861194",
        "Nome": "SARA HADASSA SANTOS DE SOUSA",
        "E-mail": "sara.hadassa@estudante.ifgoiano.edu.br",
        "Atividades": "Participa\u00e7\u00e3o no evento, Oficina 4: 5Rs da Sustentabilidade, Palestra de abertura: Indicadores de pH e o diagn\u00f3stico molecular de doen\u00e7as infecciosas: desenvolvimento de um teste molecular de baixo custo, Confer\u00eancia de abertura e momento cultural, Credenciamento vespertino",
        "A\u00e7\u00f5es": "\u00a0\u00a0 \u00a0\u00a0 \u00a0\u00a0"
    },
    "24": {
        "ID": "6125",
        "Inscrito": "70899330169",
        "Nome": "JO\\XC3\\XA3O EMANUEL PAULINO DE CARVALHO",
        "E-mail": "joao.emanuel@estudante.ifgoiano.edu.br",
        "Atividades": "Participa\u00e7\u00e3o no evento, Gincana, Oficina 3: ISSO MINHA AV\u00d3 J\u00c1 FAZIA! Uma perspectiva t\u00e9cnica da produ\u00e7\u00e3o sustent\u00e1vel de sab\u00e3o e sabonete l\u00edquido",
        "A\u00e7\u00f5es": "\u00a0\u00a0 \u00a0\u00a0 \u00a0\u00a0"
    },
    "25": {
        "ID": "6127",
        "Inscrito": "05477814152",
        "Nome": "SARA PAES ALVES",
        "E-mail": "sara.paes@estudante.ifgoiano.edu.br",
        "Atividades": "Participa\u00e7\u00e3o no evento, Gincana, Oficina 3: ISSO MINHA AV\u00d3 J\u00c1 FAZIA! Uma perspectiva t\u00e9cnica da produ\u00e7\u00e3o sustent\u00e1vel de sab\u00e3o e sabonete l\u00edquido",
        "A\u00e7\u00f5es": "\u00a0\u00a0 \u00a0\u00a0 \u00a0\u00a0"
    },
    "26": {
        "ID": "6131",
        "Inscrito": "08863080119",
        "Nome": "STEPHANIA ALVES DE JESUS",
        "E-mail": "stephania.jesus@estudante.ifgoiano.edu.br",
        "Atividades": "Participa\u00e7\u00e3o no evento",
        "A\u00e7\u00f5es": "\u00a0\u00a0 \u00a0\u00a0 \u00a0\u00a0"
    },
    "27": {
        "ID": "6180",
        "Inscrito": "70620916184",
        "Nome": "LAILA SOUZA BISPO",
        "E-mail": "laila.souza@estudante.ifgoiano.edu.br",
        "Atividades": "Participa\u00e7\u00e3o no evento, Oficina 6- Qu\u00edmica para um mundo sustent\u00e1vel: uma abordagem investigativa para o ensino de Qu\u00edmica Verde (exclusiva para discentes da Licenciatura), Palestra de abertura: Indicadores de pH e o diagn\u00f3stico molecular de doen\u00e7as infecciosas: desenvolvimento de um teste molecular de baixo custo, Confer\u00eancia de abertura e momento cultural, Cerim\u00f4nia de encerramento, Palestra de encerramento: O processo de implanta\u00e7\u00e3o de um aterro controlado em um munic\u00edpio de pequeno porte: desafios e perspectivas",
        "A\u00e7\u00f5es": "\u00a0\u00a0 \u00a0\u00a0 \u00a0\u00a0"
    },
    "28": {
        "ID": "6196",
        "Inscrito": "06462161124",
        "Nome": "JO\u00c3O PEDRO BORGES DOS SANTOS",
        "E-mail": "joao.pedro3@estudante.ifgoiano.edu.br",
        "Atividades": "Participa\u00e7\u00e3o no evento, Oficina 6- Qu\u00edmica para um mundo sustent\u00e1vel: uma abordagem investigativa para o ensino de Qu\u00edmica Verde (exclusiva para discentes da Licenciatura), Palestra de abertura: Indicadores de pH e o diagn\u00f3stico molecular de doen\u00e7as infecciosas: desenvolvimento de um teste molecular de baixo custo, Confer\u00eancia de abertura e momento cultural, Cerim\u00f4nia de encerramento, Palestra de encerramento: O processo de implanta\u00e7\u00e3o de um aterro controlado em um munic\u00edpio de pequeno porte: desafios e perspectivas",
        "A\u00e7\u00f5es": "\u00a0\u00a0 \u00a0\u00a0 \u00a0\u00a0"
    },
    "29": {
        "ID": "6213",
        "Inscrito": "78216800100",
        "Nome": "FABIO ALVES LEAO",
        "E-mail": "fabio.alves1@estudante.ifgoiano.edu.br",
        "Atividades": "Participa\u00e7\u00e3o no evento, Oficina 1- Produ\u00e7\u00e3o de alimentos a partir de plantas medicinais",
        "A\u00e7\u00f5es": "\u00a0\u00a0 \u00a0\u00a0 \u00a0\u00a0"
    },
    "30": {
        "ID": "6227",
        "Inscrito": "70981211186",
        "Nome": "PAULA VENANCIO DA SILVA",
        "E-mail": "paula.venancio@estudante.ifgoiano.edu.br",
        "Atividades": "Participa\u00e7\u00e3o no evento, Oficina 7:  Produ\u00e7\u00e3o e utiliza\u00e7\u00e3o de extratos de produtos naturais para controle de fitopat\u00f3genos  (exclusiva para discentes da Licenciatura), Oficina 1- Produ\u00e7\u00e3o de alimentos a partir de plantas medicinais, Gincana",
        "A\u00e7\u00f5es": "\u00a0\u00a0 \u00a0\u00a0 \u00a0\u00a0"
    },
    "31": {
        "ID": "6230",
        "Inscrito": "06028236179",
        "Nome": "ISABELLE LELES LAMONIER SOARES",
        "E-mail": "isabelle.leles@estudante.ifgoiano.edu.br",
        "Atividades": "Participa\u00e7\u00e3o no evento, Gincana, Palestra de abertura: Indicadores de pH e o diagn\u00f3stico molecular de doen\u00e7as infecciosas: desenvolvimento de um teste molecular de baixo custo, Confer\u00eancia de abertura e momento cultural, Cerim\u00f4nia de encerramento, Palestra de encerramento: O processo de implanta\u00e7\u00e3o de um aterro controlado em um munic\u00edpio de pequeno porte: desafios e perspectivas, Credenciamento vespertino, Credenciamento noturno",
        "A\u00e7\u00f5es": "\u00a0\u00a0 \u00a0\u00a0 \u00a0\u00a0"
    },
    "32": {
        "ID": "6238",
        "Inscrito": "06753936122",
        "Nome": "JOSE GABRIEL FLEURY DOS REIS",
        "E-mail": "jose.reis@estudante.ifgoiano.edu.br",
        "Atividades": "Participa\u00e7\u00e3o no evento, Palestra de abertura: Indicadores de pH e o diagn\u00f3stico molecular de doen\u00e7as infecciosas: desenvolvimento de um teste molecular de baixo custo, Confer\u00eancia de abertura e momento cultural, Cerim\u00f4nia de encerramento, Palestra de encerramento: O processo de implanta\u00e7\u00e3o de um aterro controlado em um munic\u00edpio de pequeno porte: desafios e perspectivas, Credenciamento vespertino, Credenciamento noturno",
        "A\u00e7\u00f5es": "\u00a0\u00a0 \u00a0\u00a0 \u00a0\u00a0"
    },
    "33": {
        "ID": "6247",
        "Inscrito": "03908061105",
        "Nome": "CAMILA VIT\u00d3RIA ALVES LOPES",
        "E-mail": "camila.lopes@estudante.ifgoiano.edu.br",
        "Atividades": "Participa\u00e7\u00e3o no evento, Oficina 1- Produ\u00e7\u00e3o de alimentos a partir de plantas medicinais, Gincana",
        "A\u00e7\u00f5es": "\u00a0\u00a0 \u00a0\u00a0 \u00a0\u00a0"
    },
    "34": {
        "ID": "6251",
        "Inscrito": "07132209108",
        "Nome": "MARCOS ANTONIO CRUZ GOULART",
        "E-mail": "marcos.goulart@estudante.ifgoiano.edu.br",
        "Atividades": "Participa\u00e7\u00e3o no evento, Gincana, Oficina 3: ISSO MINHA AV\u00d3 J\u00c1 FAZIA! Uma perspectiva t\u00e9cnica da produ\u00e7\u00e3o sustent\u00e1vel de sab\u00e3o e sabonete l\u00edquido",
        "A\u00e7\u00f5es": "\u00a0\u00a0 \u00a0\u00a0 \u00a0\u00a0"
    },
    "35": {
        "ID": "6286",
        "Inscrito": "74928767187",
        "Nome": "ANA KAROLINE SILVA MENDANHA VALDO",
        "E-mail": "ana.valdo@ifgoiano.edu.br",
        "Atividades": "Participa\u00e7\u00e3o no evento, Palestra de abertura: Indicadores de pH e o diagn\u00f3stico molecular de doen\u00e7as infecciosas: desenvolvimento de um teste molecular de baixo custo, Confer\u00eancia de abertura e momento cultural, Cerim\u00f4nia de encerramento, Palestra de encerramento: O processo de implanta\u00e7\u00e3o de um aterro controlado em um munic\u00edpio de pequeno porte: desafios e perspectivas, Credenciamento vespertino, Credenciamento noturno",
        "A\u00e7\u00f5es": "\u00a0\u00a0 \u00a0\u00a0 \u00a0\u00a0"
    },
    "36": {
        "ID": "6291",
        "Inscrito": "70075470101",
        "Nome": "JENIFFER GIOVANCA OLIVEIRA SOUZA PIRES",
        "E-mail": "jeniffer.souza@estudante.ifgoiano.edu.br",
        "Atividades": "Participa\u00e7\u00e3o no evento, Oficina 6- Qu\u00edmica para um mundo sustent\u00e1vel: uma abordagem investigativa para o ensino de Qu\u00edmica Verde (exclusiva para discentes da Licenciatura), Palestra de abertura: Indicadores de pH e o diagn\u00f3stico molecular de doen\u00e7as infecciosas: desenvolvimento de um teste molecular de baixo custo, Confer\u00eancia de abertura e momento cultural, Cerim\u00f4nia de encerramento, Palestra de encerramento: O processo de implanta\u00e7\u00e3o de um aterro controlado em um munic\u00edpio de pequeno porte: desafios e perspectivas, Credenciamento noturno",
        "A\u00e7\u00f5es": "\u00a0\u00a0 \u00a0\u00a0 \u00a0\u00a0"
    },
    "37": {
        "ID": "6297",
        "Inscrito": "06443110102",
        "Nome": "CAMILY VICT\u00d3RIA SILVA DIAS",
        "E-mail": "camily.victoria@estudante.ifgoiano.edu.br",
        "Atividades": "Participa\u00e7\u00e3o no evento, Gincana, Oficina 6- Qu\u00edmica para um mundo sustent\u00e1vel: uma abordagem investigativa para o ensino de Qu\u00edmica Verde (exclusiva para discentes da Licenciatura), Oficina 2: Ferramentas para an\u00e1lises de par\u00e2metros f\u00edsico-qu\u00edmicos de \u00e1gua de rio: Qualitativa e quantitativa",
        "A\u00e7\u00f5es": "\u00a0\u00a0 \u00a0\u00a0 \u00a0\u00a0"
    },
    "38": {
        "ID": "6298",
        "Inscrito": "03009249179",
        "Nome": "LORRANA PIRES MELO",
        "E-mail": "lorrana.pires@estudante.ifgoiano.edu.br",
        "Atividades": "Participa\u00e7\u00e3o no evento, Oficina 7:  Produ\u00e7\u00e3o e utiliza\u00e7\u00e3o de extratos de produtos naturais para controle de fitopat\u00f3genos  (exclusiva para discentes da Licenciatura), Gincana, Confer\u00eancia de abertura e momento cultural, Cerim\u00f4nia de encerramento, Palestra de encerramento: O processo de implanta\u00e7\u00e3o de um aterro controlado em um munic\u00edpio de pequeno porte: desafios e perspectivas",
        "A\u00e7\u00f5es": "\u00a0\u00a0 \u00a0\u00a0 \u00a0\u00a0"
    },
    "39": {
        "ID": "6299",
        "Inscrito": "06834869182",
        "Nome": "DAVI RIBEIRO SAMPAIO",
        "E-mail": "ribdan156@gmail.com",
        "Atividades": "Participa\u00e7\u00e3o no evento, Gincana, Oficina 6- Qu\u00edmica para um mundo sustent\u00e1vel: uma abordagem investigativa para o ensino de Qu\u00edmica Verde (exclusiva para discentes da Licenciatura), Palestra de abertura: Indicadores de pH e o diagn\u00f3stico molecular de doen\u00e7as infecciosas: desenvolvimento de um teste molecular de baixo custo, Confer\u00eancia de abertura e momento cultural, Cerim\u00f4nia de encerramento, Palestra de encerramento: O processo de implanta\u00e7\u00e3o de um aterro controlado em um munic\u00edpio de pequeno porte: desafios e perspectivas, Credenciamento vespertino, Credenciamento noturno",
        "A\u00e7\u00f5es": "\u00a0\u00a0 \u00a0\u00a0 \u00a0\u00a0"
    },
    "40": {
        "ID": "6303",
        "Inscrito": "73753670197",
        "Nome": "J\u00daLIA PEGHINI VILELA BORGES",
        "E-mail": "juliapeghini@gmail.com",
        "Atividades": "Participa\u00e7\u00e3o no evento",
        "A\u00e7\u00f5es": "\u00a0\u00a0 \u00a0\u00a0 \u00a0\u00a0"
    },
    "41": {
        "ID": "6305",
        "Inscrito": "04563685151",
        "Nome": "VIT\u00d3RIA RAFAELA",
        "E-mail": "vitoriarafavida02@gmail.com",
        "Atividades": "Participa\u00e7\u00e3o no evento, Oficina 1- Produ\u00e7\u00e3o de alimentos a partir de plantas medicinais, Gincana, Oficina 8- Cultura Maker no Ensino de Qu\u00edmica: o uso do ardu\u00edno e impress\u00e3o 3D (exclusiva para discentes da Licenciatura)",
        "A\u00e7\u00f5es": "\u00a0\u00a0 \u00a0\u00a0 \u00a0\u00a0"
    },
    "42": {
        "ID": "6311",
        "Inscrito": "03402581108",
        "Nome": "S\\XC3\\XA2MELA NUNES TAVEIRA DE MATOS",
        "E-mail": "samela.matos@estudante.ifgoiano.edu.br",
        "Atividades": "Participa\u00e7\u00e3o no evento",
        "A\u00e7\u00f5es": "\u00a0\u00a0 \u00a0\u00a0 \u00a0\u00a0"
    },
    "43": {
        "ID": "6314",
        "Inscrito": "00143860119",
        "Nome": "LUANA XAVIER CARDOSO",
        "E-mail": "luanaxaviercardoso504@gmail.com",
        "Atividades": "Participa\u00e7\u00e3o no evento, Oficina 7:  Produ\u00e7\u00e3o e utiliza\u00e7\u00e3o de extratos de produtos naturais para controle de fitopat\u00f3genos  (exclusiva para discentes da Licenciatura), Oficina 2: Ferramentas para an\u00e1lises de par\u00e2metros f\u00edsico-qu\u00edmicos de \u00e1gua de rio: Qualitativa e quantitativa",
        "A\u00e7\u00f5es": "\u00a0\u00a0 \u00a0\u00a0 \u00a0\u00a0"
    },
    "44": {
        "ID": "6335",
        "Inscrito": "94918210163",
        "Nome": "ANA MARIA RAIMUNDA FERREIRA",
        "E-mail": "Ana.maria200384@hotmail.com",
        "Atividades": "Participa\u00e7\u00e3o no evento, Oficina 7:  Produ\u00e7\u00e3o e utiliza\u00e7\u00e3o de extratos de produtos naturais para controle de fitopat\u00f3genos  (exclusiva para discentes da Licenciatura), Oficina 1- Produ\u00e7\u00e3o de alimentos a partir de plantas medicinais, Gincana",
        "A\u00e7\u00f5es": "\u00a0\u00a0 \u00a0\u00a0 \u00a0\u00a0"
    },
    "45": {
        "ID": "6341",
        "Inscrito": "05881988116",
        "Nome": "ISABELLY RODRIGUES SILVA",
        "E-mail": "isabelly.rodrigues@estudante.ifgoiano.edu.br",
        "Atividades": "Participa\u00e7\u00e3o no evento, Oficina 6- Qu\u00edmica para um mundo sustent\u00e1vel: uma abordagem investigativa para o ensino de Qu\u00edmica Verde (exclusiva para discentes da Licenciatura), Palestra de abertura: Indicadores de pH e o diagn\u00f3stico molecular de doen\u00e7as infecciosas: desenvolvimento de um teste molecular de baixo custo, Confer\u00eancia de abertura e momento cultural, Cerim\u00f4nia de encerramento, Palestra de encerramento: O processo de implanta\u00e7\u00e3o de um aterro controlado em um munic\u00edpio de pequeno porte: desafios e perspectivas, Credenciamento noturno",
        "A\u00e7\u00f5es": "\u00a0\u00a0 \u00a0\u00a0 \u00a0\u00a0"
    },
    "46": {
        "ID": "6343",
        "Inscrito": "04424528103",
        "Nome": "MARIA LUIZA PERES SANTOS",
        "E-mail": "maria.peres@estudante.ifgoiano.edu.br",
        "Atividades": "Participa\u00e7\u00e3o no evento, Oficina 4: 5Rs da Sustentabilidade, Gincana",
        "A\u00e7\u00f5es": "\u00a0\u00a0 \u00a0\u00a0 \u00a0\u00a0"
    },
    "47": {
        "ID": "6344",
        "Inscrito": "08068268197",
        "Nome": "ANA CLARA RODRIGUES DA COSTA E SILVA",
        "E-mail": "ana.costa2@estudante.ifgoiano.edu.br",
        "Atividades": "Participa\u00e7\u00e3o no evento, Oficina 1- Produ\u00e7\u00e3o de alimentos a partir de plantas medicinais, Gincana, Palestra de abertura: Indicadores de pH e o diagn\u00f3stico molecular de doen\u00e7as infecciosas: desenvolvimento de um teste molecular de baixo custo, Confer\u00eancia de abertura e momento cultural, Cerim\u00f4nia de encerramento, Palestra de encerramento: O processo de implanta\u00e7\u00e3o de um aterro controlado em um munic\u00edpio de pequeno porte: desafios e perspectivas, Credenciamento vespertino",
        "A\u00e7\u00f5es": "\u00a0\u00a0 \u00a0\u00a0 \u00a0\u00a0"
    },
    "48": {
        "ID": "6345",
        "Inscrito": "05965486138",
        "Nome": "ANNA J\u00daLIA ROQUE MAGALH\u00c3ES",
        "E-mail": "anna.roque@estudante.ifgoiano.edu.br",
        "Atividades": "Participa\u00e7\u00e3o no evento, Gincana, Palestra de abertura: Indicadores de pH e o diagn\u00f3stico molecular de doen\u00e7as infecciosas: desenvolvimento de um teste molecular de baixo custo, Confer\u00eancia de abertura e momento cultural, Credenciamento vespertino, Credenciamento noturno",
        "A\u00e7\u00f5es": "\u00a0\u00a0 \u00a0\u00a0 \u00a0\u00a0"
    },
    "49": {
        "ID": "6346",
        "Inscrito": "71162475137",
        "Nome": "MILENA GOMES MACHADO",
        "E-mail": "milena.gomes@estudante.ifgoiano.edu.br",
        "Atividades": "Participa\u00e7\u00e3o no evento, Gincana, Palestra de abertura: Indicadores de pH e o diagn\u00f3stico molecular de doen\u00e7as infecciosas: desenvolvimento de um teste molecular de baixo custo, Confer\u00eancia de abertura e momento cultural, Cerim\u00f4nia de encerramento, Palestra de encerramento: O processo de implanta\u00e7\u00e3o de um aterro controlado em um munic\u00edpio de pequeno porte: desafios e perspectivas, Oficina 5: An\u00e1lises qu\u00edmicas em microescala e suas vantagens para a Qu\u00edmica Verde, Credenciamento vespertino",
        "A\u00e7\u00f5es": "\u00a0\u00a0 \u00a0\u00a0 \u00a0\u00a0"
    },
    "50": {
        "ID": "6347",
        "Inscrito": "07646359130",
        "Nome": "GABRIEL HENRIQUE CARVALHO COSTA GOULART",
        "E-mail": "gabriel.carvalho@estudante.ifgoiano.edu.br",
        "Atividades": "Participa\u00e7\u00e3o no evento, Oficina 4: 5Rs da Sustentabilidade, Gincana",
        "A\u00e7\u00f5es": "\u00a0\u00a0 \u00a0\u00a0 \u00a0\u00a0"
    },
    "51": {
        "ID": "6348",
        "Inscrito": "04184287190",
        "Nome": "VITHOR LUCAS ITACARAMBY CUNHA",
        "E-mail": "vithor.itacaramby@estudante.ifgoiano.edu.br",
        "Atividades": "Participa\u00e7\u00e3o no evento, Oficina 1- Produ\u00e7\u00e3o de alimentos a partir de plantas medicinais, Gincana, Palestra de abertura: Indicadores de pH e o diagn\u00f3stico molecular de doen\u00e7as infecciosas: desenvolvimento de um teste molecular de baixo custo, Confer\u00eancia de abertura e momento cultural, Cerim\u00f4nia de encerramento, Palestra de encerramento: O processo de implanta\u00e7\u00e3o de um aterro controlado em um munic\u00edpio de pequeno porte: desafios e perspectivas, Credenciamento vespertino",
        "A\u00e7\u00f5es": "\u00a0\u00a0 \u00a0\u00a0 \u00a0\u00a0"
    },
    "52": {
        "ID": "6349",
        "Inscrito": "09412215126",
        "Nome": "LAURA CAVALCANTE CARVALHO",
        "E-mail": "laura.cavalcante@estudante.ifgoiano.edu.br",
        "Atividades": "Participa\u00e7\u00e3o no evento, Oficina 4: 5Rs da Sustentabilidade, Gincana",
        "A\u00e7\u00f5es": "\u00a0\u00a0 \u00a0\u00a0 \u00a0\u00a0"
    },
    "53": {
        "ID": "6350",
        "Inscrito": "07441055105",
        "Nome": "LUCAS KAUAN ALVES MORAIS",
        "E-mail": "lucas.morais@estudante.ifgoiano.edu.br",
        "Atividades": "Participa\u00e7\u00e3o no evento, Oficina 3: ISSO MINHA AV\u00d3 J\u00c1 FAZIA! Uma perspectiva t\u00e9cnica da produ\u00e7\u00e3o sustent\u00e1vel de sab\u00e3o e sabonete l\u00edquido, Palestra de abertura: Indicadores de pH e o diagn\u00f3stico molecular de doen\u00e7as infecciosas: desenvolvimento de um teste molecular de baixo custo, Confer\u00eancia de abertura e momento cultural, Cerim\u00f4nia de encerramento, Palestra de encerramento: O processo de implanta\u00e7\u00e3o de um aterro controlado em um munic\u00edpio de pequeno porte: desafios e perspectivas, Credenciamento vespertino",
        "A\u00e7\u00f5es": "\u00a0\u00a0 \u00a0\u00a0 \u00a0\u00a0"
    },
    "54": {
        "ID": "6351",
        "Inscrito": "09129052122",
        "Nome": "NIKOLLY FREITAS VITAL",
        "E-mail": "nikolly.freitas@estudante.ifgoiano.edu.br",
        "Atividades": "Participa\u00e7\u00e3o no evento, Gincana, Oficina 3: ISSO MINHA AV\u00d3 J\u00c1 FAZIA! Uma perspectiva t\u00e9cnica da produ\u00e7\u00e3o sustent\u00e1vel de sab\u00e3o e sabonete l\u00edquido, Palestra de abertura: Indicadores de pH e o diagn\u00f3stico molecular de doen\u00e7as infecciosas: desenvolvimento de um teste molecular de baixo custo, Confer\u00eancia de abertura e momento cultural, Cerim\u00f4nia de encerramento, Palestra de encerramento: O processo de implanta\u00e7\u00e3o de um aterro controlado em um munic\u00edpio de pequeno porte: desafios e perspectivas, Credenciamento vespertino",
        "A\u00e7\u00f5es": "\u00a0\u00a0 \u00a0\u00a0 \u00a0\u00a0"
    },
    "55": {
        "ID": "6352",
        "Inscrito": "08707892101",
        "Nome": "KAUA ALVES DUTRA SANTOS",
        "E-mail": "kaua.alves@estudante.ifgoiano.edu.br",
        "Atividades": "Participa\u00e7\u00e3o no evento, Oficina 4: 5Rs da Sustentabilidade, Gincana",
        "A\u00e7\u00f5es": "\u00a0\u00a0 \u00a0\u00a0 \u00a0\u00a0"
    },
    "56": {
        "ID": "6358",
        "Inscrito": "05341797116",
        "Nome": "CAMILA GOMES KIRSTEN COUTINHO",
        "E-mail": "camila.kirsten@estudante.ifgoiano.edu.br",
        "Atividades": "Participa\u00e7\u00e3o no evento, Oficina 1- Produ\u00e7\u00e3o de alimentos a partir de plantas medicinais",
        "A\u00e7\u00f5es": "\u00a0\u00a0 \u00a0\u00a0 \u00a0\u00a0"
    },
    "57": {
        "ID": "6372",
        "Inscrito": "70808257170",
        "Nome": "AMANDA LEMES FERREIRA SILVA",
        "E-mail": "amanda.lemes@estudante.ifgoiano.edu.br",
        "Atividades": "Participa\u00e7\u00e3o no evento, Oficina 1- Produ\u00e7\u00e3o de alimentos a partir de plantas medicinais, Palestra de abertura: Indicadores de pH e o diagn\u00f3stico molecular de doen\u00e7as infecciosas: desenvolvimento de um teste molecular de baixo custo, Confer\u00eancia de abertura e momento cultural, Cerim\u00f4nia de encerramento, Palestra de encerramento: O processo de implanta\u00e7\u00e3o de um aterro controlado em um munic\u00edpio de pequeno porte: desafios e perspectivas, Credenciamento noturno",
        "A\u00e7\u00f5es": "\u00a0\u00a0 \u00a0\u00a0 \u00a0\u00a0"
    },
    "58": {
        "ID": "6381",
        "Inscrito": "70630319103",
        "Nome": "GABRIELLA GON\u00c7ALVES OLIVEIRA",
        "E-mail": "gabriella.goncalves1@estudante.ifgoiano.edu.br",
        "Atividades": "Participa\u00e7\u00e3o no evento, Gincana, Confer\u00eancia de abertura e momento cultural, Cerim\u00f4nia de encerramento, Palestra de encerramento: O processo de implanta\u00e7\u00e3o de um aterro controlado em um munic\u00edpio de pequeno porte: desafios e perspectivas",
        "A\u00e7\u00f5es": "\u00a0\u00a0 \u00a0\u00a0 \u00a0\u00a0"
    },
    "59": {
        "ID": "6382",
        "Inscrito": "10838275109",
        "Nome": "GEOVANA VIEIRA ALVES",
        "E-mail": "geovana.vieira@estudante.ifgoiano.edu.br",
        "Atividades": "Participa\u00e7\u00e3o no evento, Gincana, Oficina 8- Cultura Maker no Ensino de Qu\u00edmica: o uso do ardu\u00edno e impress\u00e3o 3D (exclusiva para discentes da Licenciatura), Palestra de abertura: Indicadores de pH e o diagn\u00f3stico molecular de doen\u00e7as infecciosas: desenvolvimento de um teste molecular de baixo custo, Confer\u00eancia de abertura e momento cultural, Cerim\u00f4nia de encerramento, Palestra de encerramento: O processo de implanta\u00e7\u00e3o de um aterro controlado em um munic\u00edpio de pequeno porte: desafios e perspectivas, Credenciamento vespertino",
        "A\u00e7\u00f5es": "\u00a0\u00a0 \u00a0\u00a0 \u00a0\u00a0"
    },
    "60": {
        "ID": "6383",
        "Inscrito": "02900347106",
        "Nome": "\u00cdCARO MACEDO LOPES",
        "E-mail": "icaro.macedo@estudante.ifgoiano.edu.br",
        "Atividades": "Participa\u00e7\u00e3o no evento, Oficina 1- Produ\u00e7\u00e3o de alimentos a partir de plantas medicinais, Gincana, Confer\u00eancia de abertura e momento cultural, Cerim\u00f4nia de encerramento, Palestra de encerramento: O processo de implanta\u00e7\u00e3o de um aterro controlado em um munic\u00edpio de pequeno porte: desafios e perspectivas, Credenciamento noturno",
        "A\u00e7\u00f5es": "\u00a0\u00a0 \u00a0\u00a0 \u00a0\u00a0"
    },
    "61": {
        "ID": "6384",
        "Inscrito": "71576546101",
        "Nome": "AMANDA DE SOUSA SILVA",
        "E-mail": "amanda.sousa@estudante.ifgoiano.edu.br",
        "Atividades": "Participa\u00e7\u00e3o no evento, Gincana, Oficina 3: ISSO MINHA AV\u00d3 J\u00c1 FAZIA! Uma perspectiva t\u00e9cnica da produ\u00e7\u00e3o sustent\u00e1vel de sab\u00e3o e sabonete l\u00edquido, Palestra de abertura: Indicadores de pH e o diagn\u00f3stico molecular de doen\u00e7as infecciosas: desenvolvimento de um teste molecular de baixo custo, Confer\u00eancia de abertura e momento cultural, Cerim\u00f4nia de encerramento, Credenciamento vespertino",
        "A\u00e7\u00f5es": "\u00a0\u00a0 \u00a0\u00a0 \u00a0\u00a0"
    },
    "62": {
        "ID": "6385",
        "Inscrito": "09116738144",
        "Nome": "GABRIELA BEATRIZ VILELA ALVES",
        "E-mail": "gabriela.beatriz@estudante.ifgoiano.edu.br",
        "Atividades": "Participa\u00e7\u00e3o no evento, Palestra de abertura: Indicadores de pH e o diagn\u00f3stico molecular de doen\u00e7as infecciosas: desenvolvimento de um teste molecular de baixo custo, Confer\u00eancia de abertura e momento cultural, Cerim\u00f4nia de encerramento, Palestra de encerramento: O processo de implanta\u00e7\u00e3o de um aterro controlado em um munic\u00edpio de pequeno porte: desafios e perspectivas, Credenciamento vespertino, Credenciamento noturno",
        "A\u00e7\u00f5es": "\u00a0\u00a0 \u00a0\u00a0 \u00a0\u00a0"
    },
    "63": {
        "ID": "6386",
        "Inscrito": "71247569101",
        "Nome": "ANNA LAURA FARIA DOS SANTOS",
        "E-mail": "anna.faria@estudante.ifgoiano.edu.br",
        "Atividades": "Participa\u00e7\u00e3o no evento",
        "A\u00e7\u00f5es": "\u00a0\u00a0 \u00a0\u00a0 \u00a0\u00a0"
    },
    "64": {
        "ID": "6387",
        "Inscrito": "71264212143",
        "Nome": "LUIS EDUARDO C\\XC3\\XA2NDIDO PAES",
        "E-mail": "luis.paes@estudante.ifgoiano.edu.br",
        "Atividades": "Participa\u00e7\u00e3o no evento, Oficina 2: Ferramentas para an\u00e1lises de par\u00e2metros f\u00edsico-qu\u00edmicos de \u00e1gua de rio: Qualitativa e quantitativa",
        "A\u00e7\u00f5es": "\u00a0\u00a0 \u00a0\u00a0 \u00a0\u00a0"
    },
    "65": {
        "ID": "6390",
        "Inscrito": "09147362138",
        "Nome": "EDV\u00c2NIA MARIA LUIZA SANTOS",
        "E-mail": "edvania.santos@estudante.ifgoiano.edu.br",
        "Atividades": "Participa\u00e7\u00e3o no evento, Gincana, Oficina 3: ISSO MINHA AV\u00d3 J\u00c1 FAZIA! Uma perspectiva t\u00e9cnica da produ\u00e7\u00e3o sustent\u00e1vel de sab\u00e3o e sabonete l\u00edquido, Palestra de abertura: Indicadores de pH e o diagn\u00f3stico molecular de doen\u00e7as infecciosas: desenvolvimento de um teste molecular de baixo custo, Confer\u00eancia de abertura e momento cultural, Cerim\u00f4nia de encerramento, Palestra de encerramento: O processo de implanta\u00e7\u00e3o de um aterro controlado em um munic\u00edpio de pequeno porte: desafios e perspectivas, Credenciamento vespertino",
        "A\u00e7\u00f5es": "\u00a0\u00a0 \u00a0\u00a0 \u00a0\u00a0"
    },
    "66": {
        "ID": "6392",
        "Inscrito": "04638872123",
        "Nome": "LUISSIANY TAVARES DA SILVA",
        "E-mail": "luissiany.tavares@estudante.ifgoiano.edu.br",
        "Atividades": "Participa\u00e7\u00e3o no evento, Oficina 7:  Produ\u00e7\u00e3o e utiliza\u00e7\u00e3o de extratos de produtos naturais para controle de fitopat\u00f3genos  (exclusiva para discentes da Licenciatura), Oficina 5: An\u00e1lises qu\u00edmicas em microescala e suas vantagens para a Qu\u00edmica Verde",
        "A\u00e7\u00f5es": "\u00a0\u00a0 \u00a0\u00a0 \u00a0\u00a0"
    },
    "67": {
        "ID": "6397",
        "Inscrito": "06795545130",
        "Nome": "VALENTINA BR\\XC3\\XA1S BASSI",
        "E-mail": "valentina.bassi@estudante.ifgoiano.edu.br",
        "Atividades": "Participa\u00e7\u00e3o no evento, Oficina 4: 5Rs da Sustentabilidade, Gincana",
        "A\u00e7\u00f5es": "\u00a0\u00a0 \u00a0\u00a0 \u00a0\u00a0"
    },
    "68": {
        "ID": "6404",
        "Inscrito": "02258942110",
        "Nome": "ESTELA FRANCO DE CARVALHO",
        "E-mail": "estela.franco@estudante.ifgoiano.edu.br",
        "Atividades": "Participa\u00e7\u00e3o no evento, Gincana, Oficina 5: An\u00e1lises qu\u00edmicas em microescala e suas vantagens para a Qu\u00edmica Verde",
        "A\u00e7\u00f5es": "\u00a0\u00a0 \u00a0\u00a0 \u00a0\u00a0"
    },
    "69": {
        "ID": "6417",
        "Inscrito": "04049981190",
        "Nome": "M\\XC3\\XA1RCIA LUCIANA SOUZA NUNES",
        "E-mail": "marcia.nunes@estudante.ifgoiano.edu.br",
        "Atividades": "Participa\u00e7\u00e3o no evento, Oficina 4: 5Rs da Sustentabilidade, Gincana, Palestra de abertura: Indicadores de pH e o diagn\u00f3stico molecular de doen\u00e7as infecciosas: desenvolvimento de um teste molecular de baixo custo, Confer\u00eancia de abertura e momento cultural, Cerim\u00f4nia de encerramento, Palestra de encerramento: O processo de implanta\u00e7\u00e3o de um aterro controlado em um munic\u00edpio de pequeno porte: desafios e perspectivas",
        "A\u00e7\u00f5es": "\u00a0\u00a0 \u00a0\u00a0 \u00a0\u00a0"
    },
    "70": {
        "ID": "6419",
        "Inscrito": "04408546100",
        "Nome": "JO\u00c3O PAULO DAMASCENO RODRIGUES",
        "E-mail": "joao.damasceno@estudante.ifgoiano.edu.br",
        "Atividades": "Participa\u00e7\u00e3o no evento, Oficina 6- Qu\u00edmica para um mundo sustent\u00e1vel: uma abordagem investigativa para o ensino de Qu\u00edmica Verde (exclusiva para discentes da Licenciatura), Palestra de abertura: Indicadores de pH e o diagn\u00f3stico molecular de doen\u00e7as infecciosas: desenvolvimento de um teste molecular de baixo custo, Confer\u00eancia de abertura e momento cultural, Cerim\u00f4nia de encerramento, Palestra de encerramento: O processo de implanta\u00e7\u00e3o de um aterro controlado em um munic\u00edpio de pequeno porte: desafios e perspectivas",
        "A\u00e7\u00f5es": "\u00a0\u00a0 \u00a0\u00a0 \u00a0\u00a0"
    },
    "71": {
        "ID": "6436",
        "Inscrito": "71084004135",
        "Nome": "ERICA LEMES DE SOUSA",
        "E-mail": "erica.lemes@estudante.ifgoiano.edu.br",
        "Atividades": "Participa\u00e7\u00e3o no evento, Oficina 7:  Produ\u00e7\u00e3o e utiliza\u00e7\u00e3o de extratos de produtos naturais para controle de fitopat\u00f3genos  (exclusiva para discentes da Licenciatura), Gincana, Palestra de abertura: Indicadores de pH e o diagn\u00f3stico molecular de doen\u00e7as infecciosas: desenvolvimento de um teste molecular de baixo custo, Confer\u00eancia de abertura e momento cultural, Cerim\u00f4nia de encerramento, Palestra de encerramento: O processo de implanta\u00e7\u00e3o de um aterro controlado em um munic\u00edpio de pequeno porte: desafios e perspectivas, Oficina 5: An\u00e1lises qu\u00edmicas em microescala e suas vantagens para a Qu\u00edmica Verde, Credenciamento noturno",
        "A\u00e7\u00f5es": "\u00a0\u00a0 \u00a0\u00a0 \u00a0\u00a0"
    },
    "72": {
        "ID": "6444",
        "Inscrito": "07080577136",
        "Nome": "LUCIANA AUGUSTA LOPES",
        "E-mail": "luciana.lopes@estudante.ifgoiano.edu.br",
        "Atividades": "Participa\u00e7\u00e3o no evento, Oficina 4: 5Rs da Sustentabilidade, Gincana, Palestra de abertura: Indicadores de pH e o diagn\u00f3stico molecular de doen\u00e7as infecciosas: desenvolvimento de um teste molecular de baixo custo, Confer\u00eancia de abertura e momento cultural, Cerim\u00f4nia de encerramento, Palestra de encerramento: O processo de implanta\u00e7\u00e3o de um aterro controlado em um munic\u00edpio de pequeno porte: desafios e perspectivas",
        "A\u00e7\u00f5es": "\u00a0\u00a0 \u00a0\u00a0 \u00a0\u00a0"
    },
    "73": {
        "ID": "6452",
        "Inscrito": "04519028159",
        "Nome": "GABRIELA CORREIA SANTOS",
        "E-mail": "gabriela.correia@estudante.ifgoiano.edu.br",
        "Atividades": "Participa\u00e7\u00e3o no evento, Gincana, Credenciamento vespertino",
        "A\u00e7\u00f5es": "\u00a0\u00a0 \u00a0\u00a0 \u00a0\u00a0"
    },
    "74": {
        "ID": "6511",
        "Inscrito": "71148674179",
        "Nome": "LARA CEC\u00cdLIA ROCHA BAGATINI",
        "E-mail": "lara.bagatini@estudante.ifgoiano.edu.br",
        "Atividades": "Participa\u00e7\u00e3o no evento, Gincana, Palestra de abertura: Indicadores de pH e o diagn\u00f3stico molecular de doen\u00e7as infecciosas: desenvolvimento de um teste molecular de baixo custo, Confer\u00eancia de abertura e momento cultural, Cerim\u00f4nia de encerramento, Palestra de encerramento: O processo de implanta\u00e7\u00e3o de um aterro controlado em um munic\u00edpio de pequeno porte: desafios e perspectivas, Credenciamento vespertino, Oficina 2: Ferramentas para an\u00e1lises de par\u00e2metros f\u00edsico-qu\u00edmicos de \u00e1gua de rio: Qualitativa e quantitativa",
        "A\u00e7\u00f5es": "\u00a0\u00a0 \u00a0\u00a0 \u00a0\u00a0"
    },
    "75": {
        "ID": "6526",
        "Inscrito": "02194057196",
        "Nome": "LIDIANE JORGE MICHELINI",
        "E-mail": "lidiane.michelini@ifgoiano.edu.br",
        "Atividades": "Participa\u00e7\u00e3o no evento",
        "A\u00e7\u00f5es": "\u00a0\u00a0 \u00a0\u00a0 \u00a0\u00a0"
    },
    "76": {
        "ID": "6532",
        "Inscrito": "71298751195",
        "Nome": "MARCOS FERNANDO DE OLIVEIRA TEIXEIRA",
        "E-mail": "marcos.fernando@estudante.ifgoiano.edu.br",
        "Atividades": "Participa\u00e7\u00e3o no evento, Oficina 3: ISSO MINHA AV\u00d3 J\u00c1 FAZIA! Uma perspectiva t\u00e9cnica da produ\u00e7\u00e3o sustent\u00e1vel de sab\u00e3o e sabonete l\u00edquido, Palestra de abertura: Indicadores de pH e o diagn\u00f3stico molecular de doen\u00e7as infecciosas: desenvolvimento de um teste molecular de baixo custo, Palestra de encerramento: O processo de implanta\u00e7\u00e3o de um aterro controlado em um munic\u00edpio de pequeno porte: desafios e perspectivas",
        "A\u00e7\u00f5es": "\u00a0\u00a0 \u00a0\u00a0 \u00a0\u00a0"
    },
    "77": {
        "ID": "6536",
        "Inscrito": "70888749112",
        "Nome": "AMANDHA ALVES ARAUJO NUNES",
        "E-mail": "amandha.nunes@estudante.ifgoiano.edu.br",
        "Atividades": "Participa\u00e7\u00e3o no evento, Gincana, Palestra de abertura: Indicadores de pH e o diagn\u00f3stico molecular de doen\u00e7as infecciosas: desenvolvimento de um teste molecular de baixo custo, Confer\u00eancia de abertura e momento cultural, Cerim\u00f4nia de encerramento, Palestra de encerramento: O processo de implanta\u00e7\u00e3o de um aterro controlado em um munic\u00edpio de pequeno porte: desafios e perspectivas, Credenciamento vespertino",
        "A\u00e7\u00f5es": "\u00a0\u00a0 \u00a0\u00a0 \u00a0\u00a0"
    },
    "78": {
        "ID": "6539",
        "Inscrito": "70900289171",
        "Nome": "ST\u00c9PHANY FREITAS",
        "E-mail": "stephany.freitas@estudante.ifgoiano.edu.br",
        "Atividades": "Participa\u00e7\u00e3o no evento, Oficina 4: 5Rs da Sustentabilidade, Gincana, Palestra de abertura: Indicadores de pH e o diagn\u00f3stico molecular de doen\u00e7as infecciosas: desenvolvimento de um teste molecular de baixo custo, Cerim\u00f4nia de encerramento, Palestra de encerramento: O processo de implanta\u00e7\u00e3o de um aterro controlado em um munic\u00edpio de pequeno porte: desafios e perspectivas",
        "A\u00e7\u00f5es": "\u00a0\u00a0 \u00a0\u00a0 \u00a0\u00a0"
    },
    "79": {
        "ID": "6546",
        "Inscrito": "03913162143",
        "Nome": "GABRIEL MARTINS ALBUQUERQUE",
        "E-mail": "gabriel.albuquerque@estudante.ifgoiano.edu.br",
        "Atividades": "Participa\u00e7\u00e3o no evento, Gincana, Oficina 8- Cultura Maker no Ensino de Qu\u00edmica: o uso do ardu\u00edno e impress\u00e3o 3D (exclusiva para discentes da Licenciatura)",
        "A\u00e7\u00f5es": "\u00a0\u00a0 \u00a0\u00a0 \u00a0\u00a0"
    },
    "80": {
        "ID": "6550",
        "Inscrito": "09113491113",
        "Nome": "HELLEN CRISTINA DA SILVA LEITE",
        "E-mail": "hellen.leite@estudante.ifgoiano.edu.br",
        "Atividades": "Participa\u00e7\u00e3o no evento, Gincana",
        "A\u00e7\u00f5es": "\u00a0\u00a0 \u00a0\u00a0 \u00a0\u00a0"
    },
    "81": {
        "ID": "6568",
        "Inscrito": "04770240171",
        "Nome": "KAROLLINE ALVES DOS SANTOS",
        "E-mail": "karolline.alves@estudante.ifgoiano.edu.br",
        "Atividades": "Participa\u00e7\u00e3o no evento, Gincana, Oficina 8- Cultura Maker no Ensino de Qu\u00edmica: o uso do ardu\u00edno e impress\u00e3o 3D (exclusiva para discentes da Licenciatura), Oficina 5: An\u00e1lises qu\u00edmicas em microescala e suas vantagens para a Qu\u00edmica Verde",
        "A\u00e7\u00f5es": "\u00a0\u00a0 \u00a0\u00a0 \u00a0\u00a0"
    },
    "82": {
        "ID": "6569",
        "Inscrito": "08705205123",
        "Nome": "RAFAEL",
        "E-mail": "rafael.padilha@estudante.ifgoiano.edu.br",
        "Atividades": "Participa\u00e7\u00e3o no evento, Oficina 4: 5Rs da Sustentabilidade, Gincana, Palestra de abertura: Indicadores de pH e o diagn\u00f3stico molecular de doen\u00e7as infecciosas: desenvolvimento de um teste molecular de baixo custo, Confer\u00eancia de abertura e momento cultural, Cerim\u00f4nia de encerramento, Palestra de encerramento: O processo de implanta\u00e7\u00e3o de um aterro controlado em um munic\u00edpio de pequeno porte: desafios e perspectivas, Credenciamento vespertino",
        "A\u00e7\u00f5es": "\u00a0\u00a0 \u00a0\u00a0 \u00a0\u00a0"
    },
    "83": {
        "ID": "6572",
        "Inscrito": "70939821150",
        "Nome": "SARAH DANIELLY DE OLIVEIRA BARBOSA",
        "E-mail": "sarah.danielly@estudante.ifgoiano.edu.br",
        "Atividades": "Participa\u00e7\u00e3o no evento, Gincana, Oficina 8- Cultura Maker no Ensino de Qu\u00edmica: o uso do ardu\u00edno e impress\u00e3o 3D (exclusiva para discentes da Licenciatura), Oficina 5: An\u00e1lises qu\u00edmicas em microescala e suas vantagens para a Qu\u00edmica Verde",
        "A\u00e7\u00f5es": "\u00a0\u00a0 \u00a0\u00a0 \u00a0\u00a0"
    },
    "84": {
        "ID": "6655",
        "Inscrito": "71097500195",
        "Nome": "L\u00cdVIA KELLY DOS SANTOS DIAS",
        "E-mail": "livia.santos@estudante.ifgoiano.edu.br",
        "Atividades": "Participa\u00e7\u00e3o no evento, Oficina 7:  Produ\u00e7\u00e3o e utiliza\u00e7\u00e3o de extratos de produtos naturais para controle de fitopat\u00f3genos  (exclusiva para discentes da Licenciatura), Palestra de abertura: Indicadores de pH e o diagn\u00f3stico molecular de doen\u00e7as infecciosas: desenvolvimento de um teste molecular de baixo custo, Cerim\u00f4nia de encerramento, Palestra de encerramento: O processo de implanta\u00e7\u00e3o de um aterro controlado em um munic\u00edpio de pequeno porte: desafios e perspectivas",
        "A\u00e7\u00f5es": "\u00a0\u00a0 \u00a0\u00a0 \u00a0\u00a0"
    },
    "85": {
        "ID": "6662",
        "Inscrito": "06483973195",
        "Nome": "SUELLEN CRISTINY DA SILVA XAVIER",
        "E-mail": "suellen_cristinyxavier@hotmail.com",
        "Atividades": "Participa\u00e7\u00e3o no evento, Oficina 7:  Produ\u00e7\u00e3o e utiliza\u00e7\u00e3o de extratos de produtos naturais para controle de fitopat\u00f3genos  (exclusiva para discentes da Licenciatura), Gincana, Palestra de abertura: Indicadores de pH e o diagn\u00f3stico molecular de doen\u00e7as infecciosas: desenvolvimento de um teste molecular de baixo custo, Confer\u00eancia de abertura e momento cultural, Cerim\u00f4nia de encerramento, Palestra de encerramento: O processo de implanta\u00e7\u00e3o de um aterro controlado em um munic\u00edpio de pequeno porte: desafios e perspectivas, Oficina 5: An\u00e1lises qu\u00edmicas em microescala e suas vantagens para a Qu\u00edmica Verde, Credenciamento vespertino, Credenciamento noturno",
        "A\u00e7\u00f5es": "\u00a0\u00a0 \u00a0\u00a0 \u00a0\u00a0"
    },
    "86": {
        "ID": "6692",
        "Inscrito": "70602920124",
        "Nome": "LETICIA VIEIRA BORGES",
        "E-mail": "leticia.borges1@estudante.ifgoiano.edu.br",
        "Atividades": "Participa\u00e7\u00e3o no evento, Gincana, Credenciamento vespertino",
        "A\u00e7\u00f5es": "\u00a0\u00a0 \u00a0\u00a0 \u00a0\u00a0"
    },
    "87": {
        "ID": "6695",
        "Inscrito": "00557104173",
        "Nome": "DAVILLAS NEWTON DE OLIVEIRA CHAVES",
        "E-mail": "davillaschaves@gmail.com",
        "Atividades": "Participa\u00e7\u00e3o no evento, Gincana",
        "A\u00e7\u00f5es": "\u00a0\u00a0 \u00a0\u00a0 \u00a0\u00a0"
    },
    "88": {
        "ID": "6696",
        "Inscrito": "06428513102",
        "Nome": "GABRIELA SILVA AZEVEDO",
        "E-mail": "gabriela.azevedo@estudante.ifgoiano.edu.br",
        "Atividades": "Participa\u00e7\u00e3o no evento, Oficina 7:  Produ\u00e7\u00e3o e utiliza\u00e7\u00e3o de extratos de produtos naturais para controle de fitopat\u00f3genos  (exclusiva para discentes da Licenciatura), Palestra de abertura: Indicadores de pH e o diagn\u00f3stico molecular de doen\u00e7as infecciosas: desenvolvimento de um teste molecular de baixo custo, Confer\u00eancia de abertura e momento cultural, Cerim\u00f4nia de encerramento, Palestra de encerramento: O processo de implanta\u00e7\u00e3o de um aterro controlado em um munic\u00edpio de pequeno porte: desafios e perspectivas, Credenciamento noturno, Oficina 2: Ferramentas para an\u00e1lises de par\u00e2metros f\u00edsico-qu\u00edmicos de \u00e1gua de rio: Qualitativa e quantitativa",
        "A\u00e7\u00f5es": "\u00a0\u00a0 \u00a0\u00a0 \u00a0\u00a0"
    },
    "89": {
        "ID": "6739",
        "Inscrito": "07286730100",
        "Nome": "RIAN MOREIRA NUNES",
        "E-mail": "rian.moreira@estudante.ifgoiano.edu.br",
        "Atividades": "Participa\u00e7\u00e3o no evento, Gincana, Oficina 8- Cultura Maker no Ensino de Qu\u00edmica: o uso do ardu\u00edno e impress\u00e3o 3D (exclusiva para discentes da Licenciatura), Oficina 5: An\u00e1lises qu\u00edmicas em microescala e suas vantagens para a Qu\u00edmica Verde",
        "A\u00e7\u00f5es": "\u00a0\u00a0 \u00a0\u00a0 \u00a0\u00a0"
    },
    "90": {
        "ID": "6751",
        "Inscrito": "70495911143",
        "Nome": "HIGOR LOUREN\u00c7O ALVES",
        "E-mail": "higor.lourenco@estudante.ifgoiano.edu.br",
        "Atividades": "Participa\u00e7\u00e3o no evento, Oficina 8- Cultura Maker no Ensino de Qu\u00edmica: o uso do ardu\u00edno e impress\u00e3o 3D (exclusiva para discentes da Licenciatura), Palestra de abertura: Indicadores de pH e o diagn\u00f3stico molecular de doen\u00e7as infecciosas: desenvolvimento de um teste molecular de baixo custo, Confer\u00eancia de abertura e momento cultural, Cerim\u00f4nia de encerramento, Palestra de encerramento: O processo de implanta\u00e7\u00e3o de um aterro controlado em um munic\u00edpio de pequeno porte: desafios e perspectivas",
        "A\u00e7\u00f5es": "\u00a0\u00a0 \u00a0\u00a0 \u00a0\u00a0"
    },
    "91": {
        "ID": "6769",
        "Inscrito": "01554483239",
        "Nome": "MARKEANE COSTA DE OLIVEIRA",
        "E-mail": "oliveiramarkeane@gmail.com",
        "Atividades": "Participa\u00e7\u00e3o no evento, Oficina 6- Qu\u00edmica para um mundo sustent\u00e1vel: uma abordagem investigativa para o ensino de Qu\u00edmica Verde (exclusiva para discentes da Licenciatura), Oficina 5: An\u00e1lises qu\u00edmicas em microescala e suas vantagens para a Qu\u00edmica Verde",
        "A\u00e7\u00f5es": "\u00a0\u00a0 \u00a0\u00a0 \u00a0\u00a0"
    },
    "92": {
        "ID": "6771",
        "Inscrito": "06873463396",
        "Nome": "BRUNA HENRIQUE LOIOLA",
        "E-mail": "bruna.loiola@estudante.ifgoiano.edu.br",
        "Atividades": "Participa\u00e7\u00e3o no evento, Oficina 8- Cultura Maker no Ensino de Qu\u00edmica: o uso do ardu\u00edno e impress\u00e3o 3D (exclusiva para discentes da Licenciatura), Palestra de abertura: Indicadores de pH e o diagn\u00f3stico molecular de doen\u00e7as infecciosas: desenvolvimento de um teste molecular de baixo custo, Confer\u00eancia de abertura e momento cultural, Cerim\u00f4nia de encerramento, Palestra de encerramento: O processo de implanta\u00e7\u00e3o de um aterro controlado em um munic\u00edpio de pequeno porte: desafios e perspectivas, Credenciamento noturno",
        "A\u00e7\u00f5es": "\u00a0\u00a0 \u00a0\u00a0 \u00a0\u00a0"
    },
    "93": {
        "ID": "6788",
        "Inscrito": "71217777113",
        "Nome": "ADRIELLY FERREIRA CONCEI\u00c7\u00c3O",
        "E-mail": "adrielly.ferreira@estudante.ifgoiano.edu.br",
        "Atividades": "Participa\u00e7\u00e3o no evento, Gincana, Palestra de abertura: Indicadores de pH e o diagn\u00f3stico molecular de doen\u00e7as infecciosas: desenvolvimento de um teste molecular de baixo custo, Confer\u00eancia de abertura e momento cultural, Cerim\u00f4nia de encerramento, Palestra de encerramento: O processo de implanta\u00e7\u00e3o de um aterro controlado em um munic\u00edpio de pequeno porte: desafios e perspectivas, Credenciamento vespertino",
        "A\u00e7\u00f5es": "\u00a0\u00a0 \u00a0\u00a0 \u00a0\u00a0"
    },
    "94": {
        "ID": "6793",
        "Inscrito": "08544781160",
        "Nome": "ISADORA ROCHA MOREIRA",
        "E-mail": "isadora.rocha@estudante.ifgoiano.edu.br",
        "Atividades": "Participa\u00e7\u00e3o no evento, Gincana, Palestra de abertura: Indicadores de pH e o diagn\u00f3stico molecular de doen\u00e7as infecciosas: desenvolvimento de um teste molecular de baixo custo, Confer\u00eancia de abertura e momento cultural, Cerim\u00f4nia de encerramento, Palestra de encerramento: O processo de implanta\u00e7\u00e3o de um aterro controlado em um munic\u00edpio de pequeno porte: desafios e perspectivas, Oficina 5: An\u00e1lises qu\u00edmicas em microescala e suas vantagens para a Qu\u00edmica Verde, Credenciamento vespertino",
        "A\u00e7\u00f5es": "\u00a0\u00a0 \u00a0\u00a0 \u00a0\u00a0"
    },
    "95": {
        "ID": "6801",
        "Inscrito": "71539078159",
        "Nome": "THA\u00cdS SOUSA TEIXEIRA",
        "E-mail": "thais.teixeira1@estudante.ifgoiano.edu.br",
        "Atividades": "Participa\u00e7\u00e3o no evento, Gincana, Palestra de abertura: Indicadores de pH e o diagn\u00f3stico molecular de doen\u00e7as infecciosas: desenvolvimento de um teste molecular de baixo custo, Confer\u00eancia de abertura e momento cultural, Cerim\u00f4nia de encerramento, Palestra de encerramento: O processo de implanta\u00e7\u00e3o de um aterro controlado em um munic\u00edpio de pequeno porte: desafios e perspectivas, Oficina 5: An\u00e1lises qu\u00edmicas em microescala e suas vantagens para a Qu\u00edmica Verde, Credenciamento vespertino",
        "A\u00e7\u00f5es": "\u00a0\u00a0 \u00a0\u00a0 \u00a0\u00a0"
    },
    "96": {
        "ID": "6802",
        "Inscrito": "70727650181",
        "Nome": "BIANKA CARVALHO COSTA",
        "E-mail": "bianka.carvalho@estudante.ifgoiano.edu.br",
        "Atividades": "Participa\u00e7\u00e3o no evento, Gincana, Palestra de abertura: Indicadores de pH e o diagn\u00f3stico molecular de doen\u00e7as infecciosas: desenvolvimento de um teste molecular de baixo custo, Confer\u00eancia de abertura e momento cultural, Cerim\u00f4nia de encerramento, Palestra de encerramento: O processo de implanta\u00e7\u00e3o de um aterro controlado em um munic\u00edpio de pequeno porte: desafios e perspectivas, Oficina 5: An\u00e1lises qu\u00edmicas em microescala e suas vantagens para a Qu\u00edmica Verde, Credenciamento vespertino",
        "A\u00e7\u00f5es": "\u00a0\u00a0 \u00a0\u00a0 \u00a0\u00a0"
    },
    "97": {
        "ID": "6825",
        "Inscrito": "03614286185",
        "Nome": "NARA ALINNE NOBRE DA SILVA",
        "E-mail": "nara.silva@ifgoiano.edu.br",
        "Atividades": "Participa\u00e7\u00e3o no evento, Gincana, Oficina 8- Cultura Maker no Ensino de Qu\u00edmica: o uso do ardu\u00edno e impress\u00e3o 3D (exclusiva para discentes da Licenciatura), Palestra de abertura: Indicadores de pH e o diagn\u00f3stico molecular de doen\u00e7as infecciosas: desenvolvimento de um teste molecular de baixo custo, Confer\u00eancia de abertura e momento cultural, Cerim\u00f4nia de encerramento, Palestra de encerramento: O processo de implanta\u00e7\u00e3o de um aterro controlado em um munic\u00edpio de pequeno porte: desafios e perspectivas, Credenciamento noturno",
        "A\u00e7\u00f5es": "\u00a0\u00a0 \u00a0\u00a0 \u00a0\u00a0"
    },
    "98": {
        "ID": "6827",
        "Inscrito": "05059082121",
        "Nome": "GIOVANNA ROYTMAN SANTANA DE PAULA",
        "E-mail": "giovanna.roytman@estudante.ifgoiano.edu.br",
        "Atividades": "Participa\u00e7\u00e3o no evento, Oficina 6- Qu\u00edmica para um mundo sustent\u00e1vel: uma abordagem investigativa para o ensino de Qu\u00edmica Verde (exclusiva para discentes da Licenciatura), Palestra de abertura: Indicadores de pH e o diagn\u00f3stico molecular de doen\u00e7as infecciosas: desenvolvimento de um teste molecular de baixo custo, Confer\u00eancia de abertura e momento cultural, Cerim\u00f4nia de encerramento, Palestra de encerramento: O processo de implanta\u00e7\u00e3o de um aterro controlado em um munic\u00edpio de pequeno porte: desafios e perspectivas",
        "A\u00e7\u00f5es": "\u00a0\u00a0 \u00a0\u00a0 \u00a0\u00a0"
    },
    "99": {
        "ID": "6828",
        "Inscrito": "70856973181",
        "Nome": "TAYNARA SOUSA CANDIDA",
        "E-mail": "taynara.sousa@estudante.ifgoiano.edu.br",
        "Atividades": "Participa\u00e7\u00e3o no evento, Gincana, Oficina 6- Qu\u00edmica para um mundo sustent\u00e1vel: uma abordagem investigativa para o ensino de Qu\u00edmica Verde (exclusiva para discentes da Licenciatura), Palestra de abertura: Indicadores de pH e o diagn\u00f3stico molecular de doen\u00e7as infecciosas: desenvolvimento de um teste molecular de baixo custo, Confer\u00eancia de abertura e momento cultural, Cerim\u00f4nia de encerramento, Palestra de encerramento: O processo de implanta\u00e7\u00e3o de um aterro controlado em um munic\u00edpio de pequeno porte: desafios e perspectivas, Credenciamento vespertino, Credenciamento noturno",
        "A\u00e7\u00f5es": "\u00a0\u00a0 \u00a0\u00a0 \u00a0\u00a0"
    },
    "100": {
        "ID": "6907",
        "Inscrito": "05921187119",
        "Nome": "JO\u00c3O PAULO RODRIGUES CARVALHO",
        "E-mail": "joao.carvalho1@estudante.ifgoiano.edu.br",
        "Atividades": "Participa\u00e7\u00e3o no evento, Oficina 8- Cultura Maker no Ensino de Qu\u00edmica: o uso do ardu\u00edno e impress\u00e3o 3D (exclusiva para discentes da Licenciatura), Palestra de abertura: Indicadores de pH e o diagn\u00f3stico molecular de doen\u00e7as infecciosas: desenvolvimento de um teste molecular de baixo custo, Confer\u00eancia de abertura e momento cultural, Cerim\u00f4nia de encerramento, Palestra de encerramento: O processo de implanta\u00e7\u00e3o de um aterro controlado em um munic\u00edpio de pequeno porte: desafios e perspectivas, Credenciamento noturno",
        "A\u00e7\u00f5es": "\u00a0\u00a0 \u00a0\u00a0 \u00a0\u00a0"
    },
    "101": {
        "ID": "6908",
        "Inscrito": "04993754167",
        "Nome": "IZADORA CAVALCANTE",
        "E-mail": "izadoracavalcantecangerana@gmail.com",
        "Atividades": "Participa\u00e7\u00e3o no evento, Oficina 6- Qu\u00edmica para um mundo sustent\u00e1vel: uma abordagem investigativa para o ensino de Qu\u00edmica Verde (exclusiva para discentes da Licenciatura), Palestra de abertura: Indicadores de pH e o diagn\u00f3stico molecular de doen\u00e7as infecciosas: desenvolvimento de um teste molecular de baixo custo, Confer\u00eancia de abertura e momento cultural, Cerim\u00f4nia de encerramento, Palestra de encerramento: O processo de implanta\u00e7\u00e3o de um aterro controlado em um munic\u00edpio de pequeno porte: desafios e perspectivas, Credenciamento noturno",
        "A\u00e7\u00f5es": "\u00a0\u00a0 \u00a0\u00a0 \u00a0\u00a0"
    },
    "102": {
        "ID": "6909",
        "Inscrito": "02398349179",
        "Nome": "ALINE DIAS CABRAL",
        "E-mail": "aline.cabral@estudante.ifgoiano.edu.br",
        "Atividades": "Participa\u00e7\u00e3o no evento, Oficina 7:  Produ\u00e7\u00e3o e utiliza\u00e7\u00e3o de extratos de produtos naturais para controle de fitopat\u00f3genos  (exclusiva para discentes da Licenciatura), Gincana, Palestra de abertura: Indicadores de pH e o diagn\u00f3stico molecular de doen\u00e7as infecciosas: desenvolvimento de um teste molecular de baixo custo, Confer\u00eancia de abertura e momento cultural, Cerim\u00f4nia de encerramento, Palestra de encerramento: O processo de implanta\u00e7\u00e3o de um aterro controlado em um munic\u00edpio de pequeno porte: desafios e perspectivas, Credenciamento vespertino, Credenciamento noturno",
        "A\u00e7\u00f5es": "\u00a0\u00a0 \u00a0\u00a0 \u00a0\u00a0"
    },
    "103": {
        "ID": "6918",
        "Inscrito": "03064516116",
        "Nome": "ARIADNE GOMES CARVALHO",
        "E-mail": "ariadne.carvalho@ifgoiano.edu.br",
        "Atividades": "Participa\u00e7\u00e3o no evento, Gincana, Palestra de abertura: Indicadores de pH e o diagn\u00f3stico molecular de doen\u00e7as infecciosas: desenvolvimento de um teste molecular de baixo custo, Confer\u00eancia de abertura e momento cultural, Cerim\u00f4nia de encerramento, Palestra de encerramento: O processo de implanta\u00e7\u00e3o de um aterro controlado em um munic\u00edpio de pequeno porte: desafios e perspectivas, Credenciamento vespertino",
        "A\u00e7\u00f5es": "\u00a0\u00a0 \u00a0\u00a0 \u00a0\u00a0"
    },
    "104": {
        "ID": "6934",
        "Inscrito": "04345575109",
        "Nome": "KHAUANNE LAVIGNE SOUZA PASSOS",
        "E-mail": "khauanne.lavigne@estudante.ifgoiano.edu.br",
        "Atividades": "Participa\u00e7\u00e3o no evento, Oficina 4: 5Rs da Sustentabilidade, Gincana, Palestra de abertura: Indicadores de pH e o diagn\u00f3stico molecular de doen\u00e7as infecciosas: desenvolvimento de um teste molecular de baixo custo, Confer\u00eancia de abertura e momento cultural, Cerim\u00f4nia de encerramento, Palestra de encerramento: O processo de implanta\u00e7\u00e3o de um aterro controlado em um munic\u00edpio de pequeno porte: desafios e perspectivas, Credenciamento vespertino, Credenciamento noturno",
        "A\u00e7\u00f5es": "\u00a0\u00a0 \u00a0\u00a0 \u00a0\u00a0"
    },
    "105": {
        "ID": "6942",
        "Inscrito": "09239001107",
        "Nome": "PRISCILLA RIBEIRO PEREIRA SILVA",
        "E-mail": "priscilla.ribeiro@estudante.ifgoiano.edu.br",
        "Atividades": "Participa\u00e7\u00e3o no evento, Gincana, Palestra de abertura: Indicadores de pH e o diagn\u00f3stico molecular de doen\u00e7as infecciosas: desenvolvimento de um teste molecular de baixo custo, Palestra de encerramento: O processo de implanta\u00e7\u00e3o de um aterro controlado em um munic\u00edpio de pequeno porte: desafios e perspectivas, Oficina 2: Ferramentas para an\u00e1lises de par\u00e2metros f\u00edsico-qu\u00edmicos de \u00e1gua de rio: Qualitativa e quantitativa",
        "A\u00e7\u00f5es": "\u00a0\u00a0 \u00a0\u00a0 \u00a0\u00a0"
    },
    "106": {
        "ID": "6946",
        "Inscrito": "06873172154",
        "Nome": "BRUNA GON\u00c7ALVES BORGES",
        "E-mail": "bruna1if5@gmail.com",
        "Atividades": "Participa\u00e7\u00e3o no evento, Oficina 7:  Produ\u00e7\u00e3o e utiliza\u00e7\u00e3o de extratos de produtos naturais para controle de fitopat\u00f3genos  (exclusiva para discentes da Licenciatura), Palestra de abertura: Indicadores de pH e o diagn\u00f3stico molecular de doen\u00e7as infecciosas: desenvolvimento de um teste molecular de baixo custo, Confer\u00eancia de abertura e momento cultural, Cerim\u00f4nia de encerramento, Palestra de encerramento: O processo de implanta\u00e7\u00e3o de um aterro controlado em um munic\u00edpio de pequeno porte: desafios e perspectivas, Credenciamento noturno",
        "A\u00e7\u00f5es": "\u00a0\u00a0 \u00a0\u00a0 \u00a0\u00a0"
    },
    "107": {
        "ID": "6951",
        "Inscrito": "07964813188",
        "Nome": "HEVELLEN KETILLEY GUEDES VARGAS",
        "E-mail": "hevellen.guedes@estudante.ifgoiano.edu.br",
        "Atividades": "Participa\u00e7\u00e3o no evento, Gincana, Palestra de abertura: Indicadores de pH e o diagn\u00f3stico molecular de doen\u00e7as infecciosas: desenvolvimento de um teste molecular de baixo custo, Palestra de encerramento: O processo de implanta\u00e7\u00e3o de um aterro controlado em um munic\u00edpio de pequeno porte: desafios e perspectivas, Oficina 2: Ferramentas para an\u00e1lises de par\u00e2metros f\u00edsico-qu\u00edmicos de \u00e1gua de rio: Qualitativa e quantitativa",
        "A\u00e7\u00f5es": "\u00a0\u00a0 \u00a0\u00a0 \u00a0\u00a0"
    },
    "108": {
        "ID": "6966",
        "Inscrito": "05062391105",
        "Nome": "TIAGO OLIVEIRA SILVA",
        "E-mail": "tiago.rubi@hotmail.com",
        "Atividades": "Participa\u00e7\u00e3o no evento, Gincana, Oficina 6- Qu\u00edmica para um mundo sustent\u00e1vel: uma abordagem investigativa para o ensino de Qu\u00edmica Verde (exclusiva para discentes da Licenciatura), Palestra de abertura: Indicadores de pH e o diagn\u00f3stico molecular de doen\u00e7as infecciosas: desenvolvimento de um teste molecular de baixo custo, Cerim\u00f4nia de encerramento, Palestra de encerramento: O processo de implanta\u00e7\u00e3o de um aterro controlado em um munic\u00edpio de pequeno porte: desafios e perspectivas, Credenciamento noturno, Oficina 2: Ferramentas para an\u00e1lises de par\u00e2metros f\u00edsico-qu\u00edmicos de \u00e1gua de rio: Qualitativa e quantitativa",
        "A\u00e7\u00f5es": "\u00a0\u00a0 \u00a0\u00a0 \u00a0\u00a0"
    },
    "109": {
        "ID": "6975",
        "Inscrito": "71397040157",
        "Nome": "BRUNA DA SILVA C\u00c2NDIDO",
        "E-mail": "bruna.candido@estudante.ifgoiano.edu.br",
        "Atividades": "Participa\u00e7\u00e3o no evento, Palestra de abertura: Indicadores de pH e o diagn\u00f3stico molecular de doen\u00e7as infecciosas: desenvolvimento de um teste molecular de baixo custo, Confer\u00eancia de abertura e momento cultural, Cerim\u00f4nia de encerramento, Credenciamento vespertino, Oficina 2: Ferramentas para an\u00e1lises de par\u00e2metros f\u00edsico-qu\u00edmicos de \u00e1gua de rio: Qualitativa e quantitativa",
        "A\u00e7\u00f5es": "\u00a0\u00a0 \u00a0\u00a0 \u00a0\u00a0"
    },
    "110": {
        "ID": "6982",
        "Inscrito": "03612802119",
        "Nome": "LAURA AMARAL FERREIRA",
        "E-mail": "laura.amaral@estudante.ifgoiano.edu.br",
        "Atividades": "Participa\u00e7\u00e3o no evento, Gincana, Cerim\u00f4nia de encerramento, Palestra de encerramento: O processo de implanta\u00e7\u00e3o de um aterro controlado em um munic\u00edpio de pequeno porte: desafios e perspectivas, Oficina 2: Ferramentas para an\u00e1lises de par\u00e2metros f\u00edsico-qu\u00edmicos de \u00e1gua de rio: Qualitativa e quantitativa",
        "A\u00e7\u00f5es": "\u00a0\u00a0 \u00a0\u00a0 \u00a0\u00a0"
    },
    "111": {
        "ID": "6983",
        "Inscrito": "71257274171",
        "Nome": "ANA OL\u00cdVIA MARQUES NOGUEIRA",
        "E-mail": "ana.nogueira@estudante.ifgoiano.edu.br",
        "Atividades": "Participa\u00e7\u00e3o no evento, Gincana, Cerim\u00f4nia de encerramento, Palestra de encerramento: O processo de implanta\u00e7\u00e3o de um aterro controlado em um munic\u00edpio de pequeno porte: desafios e perspectivas, Oficina 2: Ferramentas para an\u00e1lises de par\u00e2metros f\u00edsico-qu\u00edmicos de \u00e1gua de rio: Qualitativa e quantitativa",
        "A\u00e7\u00f5es": "\u00a0\u00a0 \u00a0\u00a0 \u00a0\u00a0"
    },
    "112": {
        "ID": "7034",
        "Inscrito": "83930558149",
        "Nome": "ADRIANE DA SILVEIRA GOMES",
        "E-mail": "adriane.gomes@ifgoiano.edu.br",
        "Atividades": "Participa\u00e7\u00e3o no evento, Gincana, Oficina 8- Cultura Maker no Ensino de Qu\u00edmica: o uso do ardu\u00edno e impress\u00e3o 3D (exclusiva para discentes da Licenciatura), Palestra de abertura: Indicadores de pH e o diagn\u00f3stico molecular de doen\u00e7as infecciosas: desenvolvimento de um teste molecular de baixo custo, Confer\u00eancia de abertura e momento cultural, Cerim\u00f4nia de encerramento, Palestra de encerramento: O processo de implanta\u00e7\u00e3o de um aterro controlado em um munic\u00edpio de pequeno porte: desafios e perspectivas, Credenciamento vespertino, Oficina 2: Ferramentas para an\u00e1lises de par\u00e2metros f\u00edsico-qu\u00edmicos de \u00e1gua de rio: Qualitativa e quantitativa",
        "A\u00e7\u00f5es": "\u00a0\u00a0 \u00a0\u00a0 \u00a0\u00a0"
    },
    "113": {
        "ID": "7061",
        "Inscrito": "08379104129",
        "Nome": "ILANA ABREU DE CARVALHO",
        "E-mail": "ilana.carvalho@estudante.ifgoiano.edu.br",
        "Atividades": "Participa\u00e7\u00e3o no evento, Oficina 6- Qu\u00edmica para um mundo sustent\u00e1vel: uma abordagem investigativa para o ensino de Qu\u00edmica Verde (exclusiva para discentes da Licenciatura), Palestra de abertura: Indicadores de pH e o diagn\u00f3stico molecular de doen\u00e7as infecciosas: desenvolvimento de um teste molecular de baixo custo, Confer\u00eancia de abertura e momento cultural, Cerim\u00f4nia de encerramento, Palestra de encerramento: O processo de implanta\u00e7\u00e3o de um aterro controlado em um munic\u00edpio de pequeno porte: desafios e perspectivas, Credenciamento noturno",
        "A\u00e7\u00f5es": "\u00a0\u00a0 \u00a0\u00a0 \u00a0\u00a0"
    },
    "114": {
        "ID": "7076",
        "Inscrito": "71551153122",
        "Nome": "GEOVANNA LYSSA RODRIGUES MAR\u00c7AL",
        "E-mail": "geoanna.marcal@estudante.ifgoiano.edu.br",
        "Atividades": "Participa\u00e7\u00e3o no evento, Oficina 8- Cultura Maker no Ensino de Qu\u00edmica: o uso do ardu\u00edno e impress\u00e3o 3D (exclusiva para discentes da Licenciatura), Palestra de abertura: Indicadores de pH e o diagn\u00f3stico molecular de doen\u00e7as infecciosas: desenvolvimento de um teste molecular de baixo custo, Confer\u00eancia de abertura e momento cultural, Cerim\u00f4nia de encerramento, Palestra de encerramento: O processo de implanta\u00e7\u00e3o de um aterro controlado em um munic\u00edpio de pequeno porte: desafios e perspectivas, Credenciamento vespertino, Credenciamento noturno, Oficina 2: Ferramentas para an\u00e1lises de par\u00e2metros f\u00edsico-qu\u00edmicos de \u00e1gua de rio: Qualitativa e quantitativa",
        "A\u00e7\u00f5es": "\u00a0\u00a0 \u00a0\u00a0 \u00a0\u00a0"
    },
    "115": {
        "ID": "7096",
        "Inscrito": "71495306135",
        "Nome": "HELO\u00cdSA ALVES TEIXEIRA",
        "E-mail": "heloisa.teixeira@estudante.ifgoiano.edu.br",
        "Atividades": "Participa\u00e7\u00e3o no evento, Oficina 1- Produ\u00e7\u00e3o de alimentos a partir de plantas medicinais, Gincana",
        "A\u00e7\u00f5es": "\u00a0\u00a0 \u00a0\u00a0 \u00a0\u00a0"
    },
    "116": {
        "ID": "7099",
        "Inscrito": "09420216144",
        "Nome": "D\u00caMILLY GABRIELLY BRANQUINHO DOMINGOS",
        "E-mail": "demilly.branquinho@estudante.ifgoiano.edu.br",
        "Atividades": "Participa\u00e7\u00e3o no evento, Oficina 4: 5Rs da Sustentabilidade, Gincana, Palestra de abertura: Indicadores de pH e o diagn\u00f3stico molecular de doen\u00e7as infecciosas: desenvolvimento de um teste molecular de baixo custo, Confer\u00eancia de abertura e momento cultural, Cerim\u00f4nia de encerramento, Palestra de encerramento: O processo de implanta\u00e7\u00e3o de um aterro controlado em um munic\u00edpio de pequeno porte: desafios e perspectivas, Credenciamento noturno",
        "A\u00e7\u00f5es": "\u00a0\u00a0 \u00a0\u00a0 \u00a0\u00a0"
    },
    "117": {
        "ID": "7109",
        "Inscrito": "01339361124",
        "Nome": "STEFANE LUIZA DUARTE",
        "E-mail": "stefane.luiza@estudante.ifgoiano.edu.br",
        "Atividades": "Participa\u00e7\u00e3o no evento, Oficina 6- Qu\u00edmica para um mundo sustent\u00e1vel: uma abordagem investigativa para o ensino de Qu\u00edmica Verde (exclusiva para discentes da Licenciatura), Palestra de abertura: Indicadores de pH e o diagn\u00f3stico molecular de doen\u00e7as infecciosas: desenvolvimento de um teste molecular de baixo custo, Confer\u00eancia de abertura e momento cultural, Cerim\u00f4nia de encerramento, Palestra de encerramento: O processo de implanta\u00e7\u00e3o de um aterro controlado em um munic\u00edpio de pequeno porte: desafios e perspectivas",
        "A\u00e7\u00f5es": "\u00a0\u00a0 \u00a0\u00a0 \u00a0\u00a0"
    },
    "118": {
        "ID": "7125",
        "Inscrito": "70266105114",
        "Nome": "PIETRO BARIANI",
        "E-mail": "pietro.bariani@estudante.ifgoiano.edu.br",
        "Atividades": "Participa\u00e7\u00e3o no evento",
        "A\u00e7\u00f5es": "\u00a0\u00a0 \u00a0\u00a0 \u00a0\u00a0"
    },
    "119": {
        "ID": "7128",
        "Inscrito": "04531539176",
        "Nome": "GEOVANA FREITAS GALDINO",
        "E-mail": "geovana.freitas@estudante.ifgoiano.edu.br",
        "Atividades": "Participa\u00e7\u00e3o no evento, Oficina 1- Produ\u00e7\u00e3o de alimentos a partir de plantas medicinais, Gincana",
        "A\u00e7\u00f5es": "\u00a0\u00a0 \u00a0\u00a0 \u00a0\u00a0"
    },
    "120": {
        "ID": "7129",
        "Inscrito": "09165279131",
        "Nome": "JULIA FERNANDES ARAUJO VAZ",
        "E-mail": "julia.vaz@estudante.ifgoiano.edu.br",
        "Atividades": "Participa\u00e7\u00e3o no evento, Oficina 4: 5Rs da Sustentabilidade, Gincana, Palestra de abertura: Indicadores de pH e o diagn\u00f3stico molecular de doen\u00e7as infecciosas: desenvolvimento de um teste molecular de baixo custo, Confer\u00eancia de abertura e momento cultural, Cerim\u00f4nia de encerramento, Palestra de encerramento: O processo de implanta\u00e7\u00e3o de um aterro controlado em um munic\u00edpio de pequeno porte: desafios e perspectivas",
        "A\u00e7\u00f5es": "\u00a0\u00a0 \u00a0\u00a0 \u00a0\u00a0"
    },
    "121": {
        "ID": "7136",
        "Inscrito": "03562559135",
        "Nome": "VITOR BRENO BRANQUINHO NEVES",
        "E-mail": "vitor.breno@estudante.ifgoiano.edu.br",
        "Atividades": "Participa\u00e7\u00e3o no evento, Gincana, Palestra de abertura: Indicadores de pH e o diagn\u00f3stico molecular de doen\u00e7as infecciosas: desenvolvimento de um teste molecular de baixo custo, Confer\u00eancia de abertura e momento cultural, Credenciamento vespertino",
        "A\u00e7\u00f5es": "\u00a0\u00a0 \u00a0\u00a0 \u00a0\u00a0"
    },
    "122": {
        "ID": "7143",
        "Inscrito": "04163062173",
        "Nome": "R\u00d4MULO FILHO GUERRA MAC\u00caDO",
        "E-mail": "romulo.filho@estudante.ifgoiano.edu.br",
        "Atividades": "Participa\u00e7\u00e3o no evento, Oficina 4: 5Rs da Sustentabilidade, Gincana, Palestra de abertura: Indicadores de pH e o diagn\u00f3stico molecular de doen\u00e7as infecciosas: desenvolvimento de um teste molecular de baixo custo, Confer\u00eancia de abertura e momento cultural, Cerim\u00f4nia de encerramento, Palestra de encerramento: O processo de implanta\u00e7\u00e3o de um aterro controlado em um munic\u00edpio de pequeno porte: desafios e perspectivas, Credenciamento vespertino, Credenciamento noturno",
        "A\u00e7\u00f5es": "\u00a0\u00a0 \u00a0\u00a0 \u00a0\u00a0"
    },
    "123": {
        "ID": "7144",
        "Inscrito": "03846809179",
        "Nome": "J\\XC3\\XBALIA MANCINE OLIVEIRA E CARVALHO",
        "E-mail": "julia.mancine@estudante.ifgoiano.edu.br",
        "Atividades": "Participa\u00e7\u00e3o no evento, Oficina 4: 5Rs da Sustentabilidade, Gincana, Palestra de abertura: Indicadores de pH e o diagn\u00f3stico molecular de doen\u00e7as infecciosas: desenvolvimento de um teste molecular de baixo custo, Confer\u00eancia de abertura e momento cultural, Credenciamento vespertino, Credenciamento noturno",
        "A\u00e7\u00f5es": "\u00a0\u00a0 \u00a0\u00a0 \u00a0\u00a0"
    },
    "124": {
        "ID": "7156",
        "Inscrito": "00715186140",
        "Nome": "JORDANNA MARRA DA FONSECA COSTA",
        "E-mail": "jordanna.marra@ifgoiano.edu.br",
        "Atividades": "Participa\u00e7\u00e3o no evento, Gincana, Palestra de abertura: Indicadores de pH e o diagn\u00f3stico molecular de doen\u00e7as infecciosas: desenvolvimento de um teste molecular de baixo custo, Confer\u00eancia de abertura e momento cultural, Cerim\u00f4nia de encerramento, Palestra de encerramento: O processo de implanta\u00e7\u00e3o de um aterro controlado em um munic\u00edpio de pequeno porte: desafios e perspectivas, Credenciamento vespertino",
        "A\u00e7\u00f5es": "\u00a0\u00a0 \u00a0\u00a0 \u00a0\u00a0"
    },
    "125": {
        "ID": "7184",
        "Inscrito": "70958127131",
        "Nome": "KAUAN ARTHUR COSTA SANTOS",
        "E-mail": "kauan.arthur@estudante.ifgoiano.edu.br",
        "Atividades": "Participa\u00e7\u00e3o no evento",
        "A\u00e7\u00f5es": "\u00a0\u00a0 \u00a0\u00a0 \u00a0\u00a0"
    },
    "126": {
        "ID": "7211",
        "Inscrito": "07894804177",
        "Nome": "MATHEUS VIEIRA SILVA",
        "E-mail": "matheus.vieira1@estudante.ifgoiano.edu.br",
        "Atividades": "Participa\u00e7\u00e3o no evento, Oficina 6- Qu\u00edmica para um mundo sustent\u00e1vel: uma abordagem investigativa para o ensino de Qu\u00edmica Verde (exclusiva para discentes da Licenciatura), Cerim\u00f4nia de encerramento, Palestra de encerramento: O processo de implanta\u00e7\u00e3o de um aterro controlado em um munic\u00edpio de pequeno porte: desafios e perspectivas, Oficina 5: An\u00e1lises qu\u00edmicas em microescala e suas vantagens para a Qu\u00edmica Verde",
        "A\u00e7\u00f5es": "\u00a0\u00a0 \u00a0\u00a0 \u00a0\u00a0"
    },
    "127": {
        "ID": "7215",
        "Inscrito": "06518956186",
        "Nome": "ENIO ALECRIM DA SILVA NETO",
        "E-mail": "enio.alecrim@estudante.ifgoiano.edu.br",
        "Atividades": "Participa\u00e7\u00e3o no evento, Palestra de abertura: Indicadores de pH e o diagn\u00f3stico molecular de doen\u00e7as infecciosas: desenvolvimento de um teste molecular de baixo custo, Confer\u00eancia de abertura e momento cultural, Cerim\u00f4nia de encerramento, Palestra de encerramento: O processo de implanta\u00e7\u00e3o de um aterro controlado em um munic\u00edpio de pequeno porte: desafios e perspectivas, Credenciamento vespertino, Credenciamento noturno",
        "A\u00e7\u00f5es": "\u00a0\u00a0 \u00a0\u00a0 \u00a0\u00a0"
    },
    "128": {
        "ID": "7221",
        "Inscrito": "08534710104",
        "Nome": "GUILHERME BATISTA DA SILVA",
        "E-mail": "gs333657@gmail.com",
        "Atividades": "Participa\u00e7\u00e3o no evento, Gincana, Oficina 8- Cultura Maker no Ensino de Qu\u00edmica: o uso do ardu\u00edno e impress\u00e3o 3D (exclusiva para discentes da Licenciatura), Cerim\u00f4nia de encerramento, Palestra de encerramento: O processo de implanta\u00e7\u00e3o de um aterro controlado em um munic\u00edpio de pequeno porte: desafios e perspectivas, Oficina 2: Ferramentas para an\u00e1lises de par\u00e2metros f\u00edsico-qu\u00edmicos de \u00e1gua de rio: Qualitativa e quantitativa",
        "A\u00e7\u00f5es": "\u00a0\u00a0 \u00a0\u00a0 \u00a0\u00a0"
    },
    "129": {
        "ID": "7225",
        "Inscrito": "97476293134",
        "Nome": "THAIS MORAES ARANTES",
        "E-mail": "thais.moraes@ifgoiano.edu.br",
        "Atividades": "Participa\u00e7\u00e3o no evento, Palestra de abertura: Indicadores de pH e o diagn\u00f3stico molecular de doen\u00e7as infecciosas: desenvolvimento de um teste molecular de baixo custo, Confer\u00eancia de abertura e momento cultural, Cerim\u00f4nia de encerramento, Palestra de encerramento: O processo de implanta\u00e7\u00e3o de um aterro controlado em um munic\u00edpio de pequeno porte: desafios e perspectivas, Credenciamento vespertino",
        "A\u00e7\u00f5es": "\u00a0\u00a0 \u00a0\u00a0 \u00a0\u00a0"
    },
    "130": {
        "ID": "7247",
        "Inscrito": "00951007173",
        "Nome": "FLAVIO PINTO VIEIRA",
        "E-mail": "flavio.vieira@ifgoiano.edu.br",
        "Atividades": "Participa\u00e7\u00e3o no evento, Gincana, Oficina 3: ISSO MINHA AV\u00d3 J\u00c1 FAZIA! Uma perspectiva t\u00e9cnica da produ\u00e7\u00e3o sustent\u00e1vel de sab\u00e3o e sabonete l\u00edquido, Palestra de abertura: Indicadores de pH e o diagn\u00f3stico molecular de doen\u00e7as infecciosas: desenvolvimento de um teste molecular de baixo custo, Confer\u00eancia de abertura e momento cultural, Credenciamento vespertino, Credenciamento noturno",
        "A\u00e7\u00f5es": "\u00a0\u00a0 \u00a0\u00a0 \u00a0\u00a0"
    },
    "131": {
        "ID": "7267",
        "Inscrito": "04233152184",
        "Nome": "JOAO PAULO GRIGORIO MARTINS",
        "E-mail": "joao.grigorio@estudante.ifgoiano.edu.br",
        "Atividades": "Participa\u00e7\u00e3o no evento",
        "A\u00e7\u00f5es": "\u00a0\u00a0 \u00a0\u00a0 \u00a0\u00a0"
    },
    "132": {
        "ID": "7292",
        "Inscrito": "71243858141",
        "Nome": "ANNA MARYA ALVES VIEIRA",
        "E-mail": "anna.marya@estudante.ifgoiano.edu.br",
        "Atividades": "Participa\u00e7\u00e3o no evento, Oficina 3: ISSO MINHA AV\u00d3 J\u00c1 FAZIA! Uma perspectiva t\u00e9cnica da produ\u00e7\u00e3o sustent\u00e1vel de sab\u00e3o e sabonete l\u00edquido, Oficina 6- Qu\u00edmica para um mundo sustent\u00e1vel: uma abordagem investigativa para o ensino de Qu\u00edmica Verde (exclusiva para discentes da Licenciatura), Palestra de abertura: Indicadores de pH e o diagn\u00f3stico molecular de doen\u00e7as infecciosas: desenvolvimento de um teste molecular de baixo custo, Palestra de encerramento: O processo de implanta\u00e7\u00e3o de um aterro controlado em um munic\u00edpio de pequeno porte: desafios e perspectivas, Credenciamento vespertino",
        "A\u00e7\u00f5es": "\u00a0\u00a0 \u00a0\u00a0 \u00a0\u00a0"
    },
    "133": {
        "ID": "7311",
        "Inscrito": "17839395678",
        "Nome": "LAIANE CRISTIELLE PEREIRA DE SOUSA",
        "E-mail": "laiane.cristielle@estudante.ifgoiano.edu.br",
        "Atividades": "Participa\u00e7\u00e3o no evento",
        "A\u00e7\u00f5es": "\u00a0\u00a0 \u00a0\u00a0 \u00a0\u00a0"
    },
    "134": {
        "ID": "7318",
        "Inscrito": "04140669101",
        "Nome": "HELLEN MICAL GUIMAR\u00c3ES MENDES",
        "E-mail": "hellen.guimaraes@estudante.ifgoiano.edu.br",
        "Atividades": "Participa\u00e7\u00e3o no evento",
        "A\u00e7\u00f5es": "\u00a0\u00a0 \u00a0\u00a0 \u00a0\u00a0"
    },
    "135": {
        "ID": "7410",
        "Inscrito": "09111313102",
        "Nome": "KAU\u00c3 FALEIROS CARNEIRO",
        "E-mail": "kaua.faleiros@estudante.ifgoiano.edu.br",
        "Atividades": "Participa\u00e7\u00e3o no evento",
        "A\u00e7\u00f5es": "\u00a0\u00a0 \u00a0\u00a0 \u00a0\u00a0"
    },
    "136": {
        "ID": "7420",
        "Inscrito": "70899888135",
        "Nome": "BRUNA FELIX MOREIRA",
        "E-mail": "bruna.felix1@estudante.ifgoiano.edu.br",
        "Atividades": "Participa\u00e7\u00e3o no evento, Oficina 3: ISSO MINHA AV\u00d3 J\u00c1 FAZIA! Uma perspectiva t\u00e9cnica da produ\u00e7\u00e3o sustent\u00e1vel de sab\u00e3o e sabonete l\u00edquido, Palestra de abertura: Indicadores de pH e o diagn\u00f3stico molecular de doen\u00e7as infecciosas: desenvolvimento de um teste molecular de baixo custo, Palestra de encerramento: O processo de implanta\u00e7\u00e3o de um aterro controlado em um munic\u00edpio de pequeno porte: desafios e perspectivas, Credenciamento noturno",
        "A\u00e7\u00f5es": "\u00a0\u00a0 \u00a0\u00a0 \u00a0\u00a0"
    },
    "137": {
        "ID": "7444",
        "Inscrito": "08989310105",
        "Nome": "DIMITRI F\u00c9LIX FERREIRA NUNES",
        "E-mail": "dimitri.nunes@estudante.ifgoiano.edu.br",
        "Atividades": "Participa\u00e7\u00e3o no evento, Oficina 6- Qu\u00edmica para um mundo sustent\u00e1vel: uma abordagem investigativa para o ensino de Qu\u00edmica Verde (exclusiva para discentes da Licenciatura), Oficina 5: An\u00e1lises qu\u00edmicas em microescala e suas vantagens para a Qu\u00edmica Verde",
        "A\u00e7\u00f5es": "\u00a0\u00a0 \u00a0\u00a0 \u00a0\u00a0"
    },
    "138": {
        "ID": "7495",
        "Inscrito": "04055761104",
        "Nome": "LUIS FELIPE SANTOS GARCIA",
        "E-mail": "luis.garcia@estudante.ifgoiano.edu.br",
        "Atividades": "Participa\u00e7\u00e3o no evento, Oficina 8- Cultura Maker no Ensino de Qu\u00edmica: o uso do ardu\u00edno e impress\u00e3o 3D (exclusiva para discentes da Licenciatura), Palestra de abertura: Indicadores de pH e o diagn\u00f3stico molecular de doen\u00e7as infecciosas: desenvolvimento de um teste molecular de baixo custo, Confer\u00eancia de abertura e momento cultural, Palestra de encerramento: O processo de implanta\u00e7\u00e3o de um aterro controlado em um munic\u00edpio de pequeno porte: desafios e perspectivas, Credenciamento vespertino",
        "A\u00e7\u00f5es": "\u00a0\u00a0 \u00a0\u00a0 \u00a0\u00a0"
    },
    "139": {
        "ID": "7531",
        "Inscrito": "03192754184",
        "Nome": "DAVI CASTRO ALVES",
        "E-mail": "davi.castro@estudante.ifgoiano.edu.br",
        "Atividades": "Participa\u00e7\u00e3o no evento, Gincana, Credenciamento vespertino",
        "A\u00e7\u00f5es": "\u00a0\u00a0 \u00a0\u00a0 \u00a0\u00a0"
    },
    "140": {
        "ID": "7557",
        "Inscrito": "71102189103",
        "Nome": "CAIO REIS FERREIRA",
        "E-mail": "caio.reis@estudante.ifgoiano.edu.br",
        "Atividades": "Participa\u00e7\u00e3o no evento, Gincana, Palestra de abertura: Indicadores de pH e o diagn\u00f3stico molecular de doen\u00e7as infecciosas: desenvolvimento de um teste molecular de baixo custo, Cerim\u00f4nia de encerramento, Palestra de encerramento: O processo de implanta\u00e7\u00e3o de um aterro controlado em um munic\u00edpio de pequeno porte: desafios e perspectivas, Credenciamento vespertino, Credenciamento noturno, Oficina 2: Ferramentas para an\u00e1lises de par\u00e2metros f\u00edsico-qu\u00edmicos de \u00e1gua de rio: Qualitativa e quantitativa",
        "A\u00e7\u00f5es": "\u00a0\u00a0 \u00a0\u00a0 \u00a0\u00a0"
    },
    "141": {
        "ID": "7576",
        "Inscrito": "07244674163",
        "Nome": "JA\u00cdNE NASCIMENTO SOUSA",
        "E-mail": "jaine.nascimento@estudante.ifgoiano.edu.br",
        "Atividades": "Participa\u00e7\u00e3o no evento, Palestra de abertura: Indicadores de pH e o diagn\u00f3stico molecular de doen\u00e7as infecciosas: desenvolvimento de um teste molecular de baixo custo, Confer\u00eancia de abertura e momento cultural, Cerim\u00f4nia de encerramento, Palestra de encerramento: O processo de implanta\u00e7\u00e3o de um aterro controlado em um munic\u00edpio de pequeno porte: desafios e perspectivas, Credenciamento vespertino, Credenciamento noturno",
        "A\u00e7\u00f5es": "\u00a0\u00a0 \u00a0\u00a0 \u00a0\u00a0"
    },
    "142": {
        "ID": "7626",
        "Inscrito": "06475588156",
        "Nome": "CRISTTY HELLEN BORGES NUNES",
        "E-mail": "cristty.nunes@estudante.ifgoiano.edu.br",
        "Atividades": "Participa\u00e7\u00e3o no evento, Oficina 8- Cultura Maker no Ensino de Qu\u00edmica: o uso do ardu\u00edno e impress\u00e3o 3D (exclusiva para discentes da Licenciatura), Confer\u00eancia de abertura e momento cultural, Cerim\u00f4nia de encerramento",
        "A\u00e7\u00f5es": "\u00a0\u00a0 \u00a0\u00a0 \u00a0\u00a0"
    },
    "143": {
        "ID": "7657",
        "Inscrito": "70860186199",
        "Nome": "RAYSSA LAURINDO ARRUDA",
        "E-mail": "rayssa.laurindo@estudante.ifgoiano.edu.br",
        "Atividades": "Participa\u00e7\u00e3o no evento, Credenciamento vespertino",
        "A\u00e7\u00f5es": "\u00a0\u00a0 \u00a0\u00a0 \u00a0\u00a0"
    },
    "144": {
        "ID": "7716",
        "Inscrito": "70795731140",
        "Nome": "KAUANNE DIAS CALDEIRA SANTANA",
        "E-mail": "kauanne.dias@estudante.ifgoiano.edu.br",
        "Atividades": "Participa\u00e7\u00e3o no evento, Palestra de abertura: Indicadores de pH e o diagn\u00f3stico molecular de doen\u00e7as infecciosas: desenvolvimento de um teste molecular de baixo custo, Confer\u00eancia de abertura e momento cultural, Cerim\u00f4nia de encerramento, Palestra de encerramento: O processo de implanta\u00e7\u00e3o de um aterro controlado em um munic\u00edpio de pequeno porte: desafios e perspectivas, Credenciamento vespertino, Credenciamento noturno",
        "A\u00e7\u00f5es": "\u00a0\u00a0 \u00a0\u00a0 \u00a0\u00a0"
    },
    "145": {
        "ID": "7873",
        "Inscrito": "70821877186",
        "Nome": "ADRIAN MESSIAS DA SILVA",
        "E-mail": "adrian.messias@estudante.ifgoiano.edu.br",
        "Atividades": "Participa\u00e7\u00e3o no evento, Palestra de abertura: Indicadores de pH e o diagn\u00f3stico molecular de doen\u00e7as infecciosas: desenvolvimento de um teste molecular de baixo custo, Confer\u00eancia de abertura e momento cultural, Cerim\u00f4nia de encerramento, Palestra de encerramento: O processo de implanta\u00e7\u00e3o de um aterro controlado em um munic\u00edpio de pequeno porte: desafios e perspectivas, Oficina 5: An\u00e1lises qu\u00edmicas em microescala e suas vantagens para a Qu\u00edmica Verde",
        "A\u00e7\u00f5es": "\u00a0\u00a0 \u00a0\u00a0 \u00a0\u00a0"
    },
    "146": {
        "ID": "8026",
        "Inscrito": "70364361158",
        "Nome": "JULIO C\u00c9SAR MOREIRA DA SILVA NEVES FILHO",
        "E-mail": "julio.neves@estudante.ifgoiano.edu.br",
        "Atividades": "Participa\u00e7\u00e3o no evento",
        "A\u00e7\u00f5es": "\u00a0\u00a0 \u00a0\u00a0 \u00a0\u00a0"
    },
    "147": {
        "ID": "8044",
        "Inscrito": "06430281108",
        "Nome": "DANDARA LUANA SILVA CECCATTO",
        "E-mail": "dandara.ceccatto@estudante.ifgoiano.edu.br",
        "Atividades": "Participa\u00e7\u00e3o no evento, Oficina 1- Produ\u00e7\u00e3o de alimentos a partir de plantas medicinais, Oficina 8- Cultura Maker no Ensino de Qu\u00edmica: o uso do ardu\u00edno e impress\u00e3o 3D (exclusiva para discentes da Licenciatura), Confer\u00eancia de abertura e momento cultural, Cerim\u00f4nia de encerramento, Palestra de encerramento: O processo de implanta\u00e7\u00e3o de um aterro controlado em um munic\u00edpio de pequeno porte: desafios e perspectivas",
        "A\u00e7\u00f5es": "\u00a0\u00a0 \u00a0\u00a0 \u00a0\u00a0"
    },
    "148": {
        "ID": "8063",
        "Inscrito": "08469291122",
        "Nome": "BERNARDO DA SILVEIRA MOREIRA FELICIO",
        "E-mail": "bernardo.felicio@estudante.ifgoiano.edu.br",
        "Atividades": "Participa\u00e7\u00e3o no evento",
        "A\u00e7\u00f5es": "\u00a0\u00a0 \u00a0\u00a0 \u00a0\u00a0"
    },
    "149": {
        "ID": "8355",
        "Inscrito": "71221819100",
        "Nome": "SAMUEL HENRIQUE QUEIROZ PEREIRA",
        "E-mail": "samuel.henrique1@estudante.ifgoiano.edu.br",
        "Atividades": "Participa\u00e7\u00e3o no evento",
        "A\u00e7\u00f5es": "\u00a0\u00a0 \u00a0\u00a0 \u00a0\u00a0"
    }
}